[
    {
      "tool": "JavaScript",
      "logo": "https://img.stackshare.io/service/1209/javascript.jpeg"
    },
    {
      "tool": "GitHub",
      "logo": "https://img.stackshare.io/service/27/sBsvBbjY.png"
    },
    {
      "tool": "React",
      "logo": "https://img.stackshare.io/service/1020/OYIaJ1KK.png"
    },
    {
      "tool": "Visual Studio Code",
      "logo": "https://img.stackshare.io/service/4202/Visual_Studio_Code_logo.png"
    },
    {
      "tool": "MongoDB",
      "logo": "https://img.stackshare.io/service/1030/leaf-360x360.png"
    },
    {
      "tool": "Python",
      "logo": "https://img.stackshare.io/service/993/pUBY5pVj.png"
    },
    {
      "tool": "Firebase",
      "logo": "https://img.stackshare.io/service/116/cZLxNFZS.jpg"
    },
    {
      "tool": "Node.js",
      "logo": "https://img.stackshare.io/service/1011/n1JRsFeB_400x400.png"
    },
    {
      "tool": "Bootstrap",
      "logo": "https://img.stackshare.io/service/1101/C9QJ7V3X.png"
    },
    {
      "tool": "Docker",
      "logo": "https://img.stackshare.io/service/586/n4u37v9t_400x400.png"
    },
    {
      "tool": "Heroku",
      "logo": "https://img.stackshare.io/service/133/3wgIDj3j.png"
    },
    {
      "tool": "Git",
      "logo": "https://img.stackshare.io/service/1046/git.png"
    },
    {
      "tool": "Redis",
      "logo": "https://img.stackshare.io/service/1031/redis.png"
    },
    {
      "tool": "ExpressJS",
      "logo": "https://img.stackshare.io/service/1163/hashtag.png"
    },
    {
      "tool": "Django",
      "logo": "https://img.stackshare.io/service/994/4aGjtNQv.png"
    },
    {
      "tool": "RabbitMQ",
      "logo": "https://img.stackshare.io/service/1061/rabbit.jpg"
    },
    {
      "tool": "Java",
      "logo": "https://img.stackshare.io/service/995/K85ZWV2F.png"
    },
    {
      "tool": "MySQL",
      "logo": "https://img.stackshare.io/service/1025/logo-mysql-170x170.png"
    },
    {
      "tool": "PHP",
      "logo": "https://img.stackshare.io/service/991/hwUcGZ41_400x400.jpg"
    },
    {
      "tool": "Kubernetes",
      "logo": "https://img.stackshare.io/service/1885/21_d3cvM.png"
    },
    {
      "tool": "GitLab",
      "logo": "https://img.stackshare.io/service/880/lmalkclL.png"
    },
    {
      "tool": "React Native",
      "logo": "https://img.stackshare.io/service/2699/KoK6gHzp.jpg"
    },
    {
      "tool": "Amazon SQS",
      "logo": "https://img.stackshare.io/service/395/amazon-sqs.png"
    },
    {
      "tool": "nginx",
      "logo": "https://img.stackshare.io/service/1052/YMxUfyWf.png"
    },
    {
      "tool": "Jenkins",
      "logo": "https://img.stackshare.io/service/670/jenkins.png"
    },
    {
      "tool": "Ruby",
      "logo": "https://img.stackshare.io/service/989/ruby.png"
    },
    {
      "tool": "Kibana",
      "logo": "https://img.stackshare.io/service/1722/Image_2019-05-20_at_4.53.31_PM.png"
    },
    {
      "tool": "AWS Lambda",
      "logo": "https://img.stackshare.io/service/1909/aws-lambda.png"
    },
    {
      "tool": "Laravel",
      "logo": "https://img.stackshare.io/service/992/AcA2LnWL_400x400.jpg"
    },
    {
      "tool": "Ansible",
      "logo": "https://img.stackshare.io/service/663/ElOjna20.png"
    },
    {
      "tool": "DigitalOcean",
      "logo": "https://img.stackshare.io/service/295/Onjxs6Lw_400x400.jpg"
    },
    {
      "tool": "Selenium",
      "logo": "https://img.stackshare.io/service/1517/sbUizSli_400x400.jpg"
    },
    {
      "tool": "Go",
      "logo": "https://img.stackshare.io/service/1005/O6AczwfV_400x400.png"
    },
    {
      "tool": "Atom",
      "logo": "https://img.stackshare.io/service/648/QbnVqgX4.png"
    },
    {
      "tool": "Zendesk",
      "logo": "https://img.stackshare.io/service/70/ObVtJEgP_400x400.png"
    },
    {
      "tool": "Datadog",
      "logo": "https://img.stackshare.io/service/669/5cX1R9Rr_400x400.jpg"
    },
    {
      "tool": "Vuetify",
      "logo": "https://img.stackshare.io/service/6163/PzNbCwXH.jpg"
    },
    {
      "tool": "Metabase",
      "logo": "https://img.stackshare.io/service/3860/4unoiuHt_400x400.jpg"
    },
    {
      "tool": "Vercel",
      "logo": "https://img.stackshare.io/service/7618/bHjpwZem_400x400.png"
    },
    {
      "tool": "StatusPage.io",
      "logo": "https://img.stackshare.io/service/279/sp-logo-blue-white-background.jpg"
    },
    {
      "tool": "npm",
      "logo": "https://img.stackshare.io/service/1120/lejvzrnlpb308aftn31u.png"
    },
    {
      "tool": "Postman",
      "logo": "https://img.stackshare.io/service/1336/xWMRvm_5_400x400.png"
    },
    {
      "tool": "CSS 3",
      "logo": "https://img.stackshare.io/service/6727/css.png"
    },
    {
      "tool": "WordPress",
      "logo": "https://img.stackshare.io/service/250/logo.png"
    },
    {
      "tool": "Amazon S3",
      "logo": "https://img.stackshare.io/service/25/amazon-s3.png"
    },
    {
      "tool": "C#",
      "logo": "https://img.stackshare.io/service/1015/1200px-C_Sharp_wordmark.svg.png"
    },
    {
      "tool": "Amazon EC2",
      "logo": "https://img.stackshare.io/service/18/amazon-ec2.png"
    },
    {
      "tool": "Bitbucket",
      "logo": "https://img.stackshare.io/service/28/35O2KIRX_400x400.jpg"
    },
    {
      "tool": "Webpack",
      "logo": "https://img.stackshare.io/service/1682/IMG_4636.PNG"
    },
    {
      "tool": "Sublime Text",
      "logo": "https://img.stackshare.io/service/642/SublimeText_Master_012312_icon.png"
    },
    {
      "tool": "VirtualBox",
      "logo": "https://img.stackshare.io/service/774/vbox_94px.png"
    },
    {
      "tool": "CloudFlare",
      "logo": "https://img.stackshare.io/service/15/twitter-profile-400x400.png"
    },
    {
      "tool": "Spring Boot",
      "logo": "https://img.stackshare.io/service/2927/nPzvMuo2_400x400.png"
    },
    {
      "tool": "Kafka",
      "logo": "https://img.stackshare.io/service/1063/kazUJooF_400x400.jpg"
    },
    {
      "tool": "Yarn",
      "logo": "https://img.stackshare.io/service/5848/44mC-kJ3.jpg"
    },
    {
      "tool": "Amazon RDS",
      "logo": "https://img.stackshare.io/service/232/amazon-rds.png"
    },
    {
      "tool": "WebStorm",
      "logo": "https://img.stackshare.io/service/1455/icon_WebStorm.png"
    },
    {
      "tool": "Sentry",
      "logo": "https://img.stackshare.io/service/191/lzoDXqf-.png"
    },
    {
      "tool": "Asana",
      "logo": "https://img.stackshare.io/service/108/asana.png"
    },
    {
      "tool": "C++",
      "logo": "https://img.stackshare.io/service/1049/cplusplus.png"
    },
    {
      "tool": "Ionic",
      "logo": "https://img.stackshare.io/service/876/bYMCvtHD_400x400.jpg"
    },
    {
      "tool": "Socket.IO",
      "logo": "https://img.stackshare.io/service/1161/vI0ZZlhZ_400x400.png"
    },
    {
      "tool": "Symfony",
      "logo": "https://img.stackshare.io/service/1197/logosf_positif_03_icon.png"
    },
    {
      "tool": "Mixpanel",
      "logo": "https://img.stackshare.io/service/60/Dmy5RfTT_400x400.png"
    },
    {
      "tool": "Figma",
      "logo": "https://img.stackshare.io/service/7007/MFYQOphW_400x400.jpg"
    },
    {
      "tool": "Sketch",
      "logo": "https://img.stackshare.io/service/4561/c07jH7QS.jpg"
    },
    {
      "tool": "Next.js",
      "logo": "https://img.stackshare.io/service/5936/nextjs.png"
    },
    {
      "tool": "SonarQube",
      "logo": "https://img.stackshare.io/service/2638/zIVhxKyn_400x400.png"
    },
    {
      "tool": "CodeIgniter",
      "logo": "https://img.stackshare.io/service/1195/ci_logo.png"
    },
    {
      "tool": "AWS Elastic Beanstalk",
      "logo": "https://img.stackshare.io/service/210/aws-elastic-beanstalk.png"
    },
    {
      "tool": "Appium",
      "logo": "https://img.stackshare.io/service/2855/0KVJyYNC_400x400.jpg"
    },
    {
      "tool": "Superset",
      "logo": "https://img.stackshare.io/service/4908/superset2.png"
    },
    {
      "tool": "Contentful",
      "logo": "https://img.stackshare.io/service/672/Contentful_white_logo.png"
    },
    {
      "tool": "Foundation",
      "logo": "https://img.stackshare.io/service/1105/ocLJW3ku_400x400.jpg"
    },
    {
      "tool": "Amazon LightSail",
      "logo": "https://img.stackshare.io/service/6094/amazon-lightsail.png"
    },
    {
      "tool": "Apigee",
      "logo": "https://img.stackshare.io/service/4215/6f72b788786c25b956aac477099a23ed_400x400.png"
    },
    {
      "tool": "Vue Native",
      "logo": "https://img.stackshare.io/service/9117/logo.png"
    },
    {
      "tool": "Ghost",
      "logo": "https://img.stackshare.io/service/1228/XRKixLnT_400x400.png"
    },
    {
      "tool": "Back4App",
      "logo": "https://img.stackshare.io/service/10084/dwM1HGjZ_400x400.jpg"
    },
    {
      "tool": "Campaign Monitor",
      "logo": "https://img.stackshare.io/service/48/GYLX84mG_400x400.jpg"
    },
    {
      "tool": "Zenkit",
      "logo": "https://img.stackshare.io/service/7153/Zenkit_Logo_Icon_square.png"
    },
    {
      "tool": "Convox",
      "logo": "https://img.stackshare.io/service/3368/preview.png"
    },
    {
      "tool": "Status.io",
      "logo": "https://img.stackshare.io/service/1373/statusio_icon.png"
    },
    {
      "tool": "Push.js",
      "logo": "https://img.stackshare.io/no-img-open-source.png"
    },
    {
      "tool": "Kustomize",
      "logo": "https://img.stackshare.io/service/12670/kustomize.png"
    },
    {
      "tool": "HTML5",
      "logo": "https://img.stackshare.io/service/2538/kEpgHiC9.png"
    },
    {
      "tool": "Slack",
      "logo": "https://img.stackshare.io/service/675/RNiSRYOF_400x400.jpg"
    },
    {
      "tool": "jQuery",
      "logo": "https://img.stackshare.io/service/1021/lxEKmMnB_400x400.jpg"
    },
    {
      "tool": "PostgreSQL",
      "logo": "https://img.stackshare.io/service/1028/ASOhU5xJ.png"
    },
    {
      "tool": "Google Drive",
      "logo": "https://img.stackshare.io/service/148/5qxhymf609p5sizjjqvz.png"
    },
    {
      "tool": "ES6",
      "logo": "https://img.stackshare.io/service/4109/16407404782_8b9c57eab3.jpg"
    },
    {
      "tool": "Google Analytics",
      "logo": "https://img.stackshare.io/service/64/cU74ahCn_400x400.jpg"
    },
    {
      "tool": "Jira",
      "logo": "https://img.stackshare.io/service/154/Qifq4jpS_400x400.jpg"
    },
    {
      "tool": "AngularJS",
      "logo": "https://img.stackshare.io/service/1019/square.png"
    },
    {
      "tool": "Visual Studio",
      "logo": "https://img.stackshare.io/service/1451/SR2hUhQN.png"
    },
    {
      "tool": "Trello",
      "logo": "https://img.stackshare.io/service/109/-CvHThPk_400x400.jpg"
    },
    {
      "tool": "IntelliJ IDEA",
      "logo": "https://img.stackshare.io/service/1453/icon_IntelliJIDEA.png"
    },
    {
      "tool": "GraphQL",
      "logo": "https://img.stackshare.io/service/3820/12972006.png"
    },
    {
      "tool": "Elasticsearch",
      "logo": "https://img.stackshare.io/service/841/Image_2019-05-20_at_4.58.04_PM.png"
    },
    {
      "tool": "Redux",
      "logo": "https://img.stackshare.io/service/4074/13142323.png"
    },
    {
      "tool": "Apache HTTP Server",
      "logo": "https://img.stackshare.io/service/1051/fab.os.logo.apache.200.15011_400x400.jpg"
    },
    {
      "tool": "Dropbox",
      "logo": "https://img.stackshare.io/service/146/cbe630c29a62e283cef31afc5c4471da.png"
    },
    {
      "tool": "Confluence",
      "logo": "https://img.stackshare.io/service/769/5_z16TbH_400x400.jpg"
    },
    {
      "tool": "Vim",
      "logo": "https://img.stackshare.io/service/644/vim_logo.png"
    },
    {
      "tool": "GitHub Pages",
      "logo": "https://img.stackshare.io/service/683/sBsvBbjY.png"
    },
    {
      "tool": "Android Studio",
      "logo": "https://img.stackshare.io/service/1447/AyreX9yf.jpeg"
    },
    {
      "tool": "Docker Compose",
      "logo": "https://img.stackshare.io/service/3136/docker-compose.png"
    },
    {
      "tool": "Microsoft Azure",
      "logo": "https://img.stackshare.io/service/213/W9gT7hZo.png"
    },
    {
      "tool": "ESLint",
      "logo": "https://img.stackshare.io/service/3337/Q4L7Jncy.jpg"
    },
    {
      "tool": "SQLite",
      "logo": "https://img.stackshare.io/service/1071/sqlite.jpg"
    },
    {
      "tool": "Xcode",
      "logo": "https://img.stackshare.io/service/1448/xcode.png"
    },
    {
      "tool": "Mailchimp",
      "logo": "https://img.stackshare.io/service/47/69XlPqVT.png"
    },
    {
      "tool": "Terraform",
      "logo": "https://img.stackshare.io/service/1276/terraform.png"
    },
    {
      "tool": "Grafana",
      "logo": "https://img.stackshare.io/service/2645/rhtKuA9t.png"
    },
    {
      "tool": "Amazon EC2 Container Service",
      "logo": "https://img.stackshare.io/service/1908/amazon-ecs.png"
    },
    {
      "tool": "Google AdSense",
      "logo": "https://img.stackshare.io/service/5137/xvWejEyc_400x400.jpg"
    },
    {
      "tool": "Amazon Route 53",
      "logo": "https://img.stackshare.io/service/38/amazon-route-53.png"
    },
    {
      "tool": "Microsoft IIS",
      "logo": "https://img.stackshare.io/service/1056/J5gFiHbG.png"
    },
    {
      "tool": "Shopify",
      "logo": "https://img.stackshare.io/service/266/xDoyHgZW_400x400.png"
    },
    {
      "tool": "SourceTree",
      "logo": "https://img.stackshare.io/service/1599/sourcetree.png"
    },
    {
      "tool": "Vagrant",
      "logo": "https://img.stackshare.io/service/768/150px-Vagrant.png"
    },
    {
      "tool": "New Relic",
      "logo": "https://img.stackshare.io/service/103/yEDRfH2o.jpeg"
    },
    {
      "tool": "Memcached",
      "logo": "https://img.stackshare.io/service/1040/memcached-logo-200x152.png"
    },
    {
      "tool": "Grunt",
      "logo": "https://img.stackshare.io/service/845/falgg2jybmhgk16y62lr.png"
    },
    {
      "tool": "C",
      "logo": "https://img.stackshare.io/no-img-open-source.png"
    },
    {
      "tool": "Modernizr",
      "logo": "https://img.stackshare.io/service/2440/9TeXWBzR_400x400.jpg"
    },
    {
      "tool": "TensorFlow",
      "logo": "https://img.stackshare.io/service/4717/FtFnqC38_400x400.png"
    },
    {
      "tool": "Gatsby",
      "logo": "https://ucarecdn.com/04b55b4e-0ecc-4003-a89e-98f674075b3e/"
    },
    {
      "tool": "Varnish",
      "logo": "https://img.stackshare.io/service/1073/mPwTb3BF.png"
    },
    {
      "tool": ".NET",
      "logo": "https://img.stackshare.io/service/1014/IoPy1dce_400x400.png"
    },
    {
      "tool": "Rust",
      "logo": "https://img.stackshare.io/service/1070/v7txhrjp9pdqrkdtxxp0.png"
    },
    {
      "tool": "Jest",
      "logo": "https://img.stackshare.io/service/830/jest.png"
    },
    {
      "tool": "Mandrill",
      "logo": "https://img.stackshare.io/service/46/0skjzkftgup526281tkn.png"
    },
    {
      "tool": "Linux",
      "logo": "https://img.stackshare.io/service/10483/linux.png"
    },
    {
      "tool": "Dart",
      "logo": "https://img.stackshare.io/service/1646/Twitter-02.png"
    },
    {
      "tool": "Amazon DynamoDB",
      "logo": "https://img.stackshare.io/service/389/amazon-dynamodb.png"
    },
    {
      "tool": "NestJS",
      "logo": "https://img.stackshare.io/service/8747/4zsOyxko_400x400.jpg"
    },
    {
      "tool": "Jupyter",
      "logo": "https://img.stackshare.io/service/4190/fGBUdNf__400x400.jpg"
    },
    {
      "tool": "Tableau",
      "logo": "https://img.stackshare.io/service/2584/ZadESXl4_400x400.jpg"
    },
    {
      "tool": "PyTorch",
      "logo": "https://img.stackshare.io/service/8171/YYpjkbVn_400x400.jpg"
    },
    {
      "tool": "Discord",
      "logo": "https://img.stackshare.io/service/4418/gT8yKJa7.jpg"
    },
    {
      "tool": "scikit-learn",
      "logo": "https://img.stackshare.io/service/2657/scikit-learn-logo.png"
    },
    {
      "tool": "Material-UI",
      "logo": "https://img.stackshare.io/service/1904/_.png"
    },
    {
      "tool": "Unity",
      "logo": "https://img.stackshare.io/service/2084/CGKUrcD9_400x400.jpg"
    },
    {
      "tool": "Cypress",
      "logo": "https://img.stackshare.io/service/9231/pXI1GDHW_400x400.jpg"
    },
    {
      "tool": "Django REST framework",
      "logo": "https://img.stackshare.io/service/1630/New_Project__67_.png"
    },
    {
      "tool": "Telegram",
      "logo": "https://img.stackshare.io/service/3940/m6BFtJQW_400x400.png"
    },
    {
      "tool": "Google Chrome",
      "logo": "https://img.stackshare.io/service/2950/1200px-Google_Chrome_icon__September_2014_.svg.png"
    },
    {
      "tool": "Azure SQL Database",
      "logo": "https://img.stackshare.io/service/3433/OJB_wH-7_400x400.jpg"
    },
    {
      "tool": "Windows",
      "logo": "https://img.stackshare.io/service/2881/U54M_YbJ_400x400.jpg"
    },
    {
      "tool": "Docker Swarm",
      "logo": "https://img.stackshare.io/service/3177/preview.png"
    },
    {
      "tool": "Perl",
      "logo": "https://img.stackshare.io/service/1048/perl.png"
    },
    {
      "tool": "Mongoose",
      "logo": "https://img.stackshare.io/service/1231/0TXzZU7W_400x400.jpg"
    },
    {
      "tool": "Amazon API Gateway",
      "logo": "https://img.stackshare.io/service/3299/aws-api-gateway.png"
    },
    {
      "tool": "Minio",
      "logo": "https://img.stackshare.io/service/4485/gTawkyAA.png"
    },
    {
      "tool": "pytest",
      "logo": "https://img.stackshare.io/service/4586/Lu99Qe0Z_400x400.png"
    },
    {
      "tool": "Netlify CMS",
      "logo": "https://img.stackshare.io/service/7613/YIgPht1s_400x400.jpg"
    },
    {
      "tool": "Puppeteer",
      "logo": "https://img.stackshare.io/service/7553/puppeteer.png"
    },
    {
      "tool": "iTerm2",
      "logo": "https://img.stackshare.io/service/3000/iTerm.png"
    },
    {
      "tool": "Amplitude",
      "logo": "https://img.stackshare.io/service/640/2GWfH_eb_400x400.jpg"
    },
    {
      "tool": "Amazon ElastiCache",
      "logo": "https://img.stackshare.io/service/392/amazon-elasticache.png"
    },
    {
      "tool": "Phoenix Framework",
      "logo": "https://img.stackshare.io/service/3262/-s9uoLIN.png"
    },
    {
      "tool": "Amazon Cognito",
      "logo": "https://img.stackshare.io/service/1093/16ffae8c667bdbc6a4969f6f02090652.png"
    },
    {
      "tool": "Amazon SNS",
      "logo": "https://img.stackshare.io/service/396/amazon-sns.png"
    },
    {
      "tool": "Firefox",
      "logo": "https://img.stackshare.io/service/8705/768px-Firefox_Logo__2017.svg.png"
    },
    {
      "tool": "Qt",
      "logo": "https://img.stackshare.io/service/2449/qt-icon.png"
    },
    {
      "tool": "Ant Design",
      "logo": "https://img.stackshare.io/service/6112/12101536.png"
    },
    {
      "tool": "Elm",
      "logo": "https://img.stackshare.io/service/4009/cZHhsF-c_normal.png"
    },
    {
      "tool": "Strapi",
      "logo": "https://ucarecdn.com/2704c731-d8b8-4832-a05e-68882e8c565f/"
    },
    {
      "tool": "Webflow",
      "logo": "https://img.stackshare.io/service/587/truotQk9.png"
    },
    {
      "tool": "Xamarin",
      "logo": "https://img.stackshare.io/service/211/RDXWoY7W.png"
    },
    {
      "tool": "Magento",
      "logo": "https://img.stackshare.io/service/1769/wcU6vWxh_400x400.jpg"
    },
    {
      "tool": "ActiveMQ",
      "logo": "https://img.stackshare.io/service/1062/vlz__1_.png"
    },
    {
      "tool": "Auth0",
      "logo": "https://img.stackshare.io/service/601/5Nm3jtVh.jpeg"
    },
    {
      "tool": "Packer",
      "logo": "https://img.stackshare.io/service/967/packer.png"
    },
    {
      "tool": "InfluxDB",
      "logo": "https://img.stackshare.io/service/1396/fc3a45a16c93d59408e04097e8bef1e8.png"
    },
    {
      "tool": "Packer",
      "logo": "https://img.stackshare.io/service/967/packer.png"
    },
    {
      "tool": "Homebrew",
      "logo": "https://img.stackshare.io/service/2404/homebrew.png"
    },
    {
      "tool": "Celery",
      "logo": "https://img.stackshare.io/service/1075/celery.png"
    },
    {
      "tool": "Pug",
      "logo": "https://img.stackshare.io/service/1175/pug.png"
    },
    {
      "tool": "AppDynamics",
      "logo": "https://img.stackshare.io/service/105/C0eOfY-7.png"
    },
    {
      "tool": "Puppet Labs",
      "logo": "https://img.stackshare.io/service/421/954f7381089ac290b4690c5ffd9dd7d3.png"
    },
    {
      "tool": "Scaleway",
      "logo": "https://img.stackshare.io/service/2730/scaleway.png"
    },
    {
      "tool": "Neovim",
      "logo": "https://img.stackshare.io/service/983/XDy-S1r6.png"
    },
    {
      "tool": "Nagios",
      "logo": "https://img.stackshare.io/service/786/3gaoi2h254k0canb4hxj.png"
    },
    {
      "tool": "AWS CodeDeploy",
      "logo": "https://img.stackshare.io/service/1888/aws-codedeploy.png"
    },
    {
      "tool": "Apache Cordova",
      "logo": "https://img.stackshare.io/service/1716/cordova_256.png"
    },
    {
      "tool": "Haskell",
      "logo": "https://img.stackshare.io/service/1069/oCgm29k9.png"
    },
    {
      "tool": "Bulma",
      "logo": "https://img.stackshare.io/service/5204/bulma-logo.png"
    },
    {
      "tool": "Blockchain",
      "logo": "https://img.stackshare.io/service/10608/ciDiP1gY_400x400.jpg"
    },
    {
      "tool": "Optimizely",
      "logo": "https://img.stackshare.io/service/61/preview.png"
    },
    {
      "tool": "Hasura",
      "logo": "https://img.stackshare.io/service/6590/hasura_logo_vertical_black.png"
    },
    {
      "tool": "AWS Step Functions",
      "logo": "https://img.stackshare.io/service/6089/SWF-e64610d24b6e458c257f1105d8aa926f4a524182.png"
    },
    {
      "tool": "Spring Framework",
      "logo": "https://img.stackshare.io/service/2006/spring-framework-project-logo.png"
    },
    {
      "tool": "Formik",
      "logo": "https://img.stackshare.io/service/8846/preview.png"
    },
    {
      "tool": "Mustache",
      "logo": "https://img.stackshare.io/service/1142/197655.png"
    },
    {
      "tool": "Pusher",
      "logo": "https://img.stackshare.io/service/115/preview.png"
    },
    {
      "tool": "Wix",
      "logo": "https://img.stackshare.io/service/4656/tvOXJHAG_400x400.png"
    },
    {
      "tool": "1Password",
      "logo": "https://img.stackshare.io/service/7122/jPhaQEQv_400x400.jpg"
    },
    {
      "tool": "Smartlook",
      "logo": "https://img.stackshare.io/service/5716/7N5Ba77R_400x400.jpg"
    },
    {
      "tool": "Spring Framework",
      "logo": "https://img.stackshare.io/service/2006/spring-framework-project-logo.png"
    },
    {
      "tool": "Azure Pipelines",
      "logo": "https://img.stackshare.io/service/10164/528389819366_e7a0672f0480b3e98d21_512.png"
    },
    {
      "tool": "Ambassador",
      "logo": "https://img.stackshare.io/service/9175/uedtT4ju_400x400.jpg"
    },
    {
      "tool": "Jinja",
      "logo": "https://img.stackshare.io/service/2303/New_Project__20_.png"
    },
    {
      "tool": "PrestaShop",
      "logo": "https://img.stackshare.io/service/925/C6U2rHtG_400x400.jpg"
    },
    {
      "tool": "TailsOS",
      "logo": "https://img.stackshare.io/service/12587/x-ebkKhu_400x400.png"
    },
    {
      "tool": "Supervisord",
      "logo": "https://img.stackshare.io/service/1720/513914.png"
    },
    {
      "tool": "Bugsnag",
      "logo": "https://img.stackshare.io/service/150/square-logo-small-midnight.png"
    },
    {
      "tool": "Spring MVC",
      "logo": "https://img.stackshare.io/service/5493/wbCRW-u6_400x400.png"
    },
    {
      "tool": "Authy",
      "logo": "https://img.stackshare.io/service/364/J64iXv8S.png"
    },
    {
      "tool": "Git Flow",
      "logo": "https://img.stackshare.io/no-img-open-source.png"
    },
    {
      "tool": "Yii",
      "logo": "https://img.stackshare.io/service/1200/logo-body2.png"
    },
    {
      "tool": "Code Climate",
      "logo": "https://img.stackshare.io/service/305/KFgYaUkK.png"
    },
    {
      "tool": "ZeroMQ",
      "logo": "https://img.stackshare.io/service/1064/zeromq.png"
    },
    {
      "tool": "Apache Impala",
      "logo": "https://img.stackshare.io/service/963/Ggg-dCeV.png"
    },
    {
      "tool": "RocketChat",
      "logo": "https://img.stackshare.io/service/3124/14EIApTi_400x400.jpg"
    },
    {
      "tool": "Directus",
      "logo": "https://img.stackshare.io/service/5733/I0Ix_KWZ.jpg"
    },
    {
      "tool": "ReSharper",
      "logo": "https://img.stackshare.io/service/1831/lni0by_I_400x400.png"
    },
    {
      "tool": "Cube.js",
      "logo": "https://img.stackshare.io/service/9782/XJjwHWi__400x400.jpg"
    },
    {
      "tool": "OpenFaaS",
      "logo": "https://img.stackshare.io/service/9681/27013154.png"
    },
    {
      "tool": "Amazon MQ",
      "logo": "https://img.stackshare.io/service/7971/FrshWMKt_400x400.jpg"
    },
    {
      "tool": "AdonisJS",
      "logo": "https://img.stackshare.io/service/6439/AlIKY7xr_400x400.jpg"
    },
    {
      "tool": "PostGraphile",
      "logo": "https://img.stackshare.io/service/4991/postgraphile.optimized.square.png"
    },
    {
      "tool": "Apache Pulsar",
      "logo": "https://img.stackshare.io/service/5706/wFcLUbwd_400x400.jpg"
    },
    {
      "tool": "PhoneGap",
      "logo": "https://img.stackshare.io/service/777/NgaEDjHt.jpg"
    },
    {
      "tool": "CodeSandbox",
      "logo": "https://img.stackshare.io/service/7434/Screen_20Shot_202017-08-11_20at_205.55.05_20AM.png"
    },
    {
      "tool": "Highcharts",
      "logo": "https://img.stackshare.io/service/1435/Vx4_Psj1.png"
    },
    {
      "tool": "JBoss",
      "logo": "https://img.stackshare.io/service/2188/unnamed.jpg"
    },
    {
      "tool": "WebRTC",
      "logo": "https://img.stackshare.io/service/2262/xDgK1jYK_400x400.jpg"
    },
    {
      "tool": "PhoneGap",
      "logo": "https://img.stackshare.io/service/777/NgaEDjHt.jpg"
    },
    {
      "tool": "minikube",
      "logo": "https://img.stackshare.io/service/9409/preview.png"
    },
    {
      "tool": "OpenFaaS",
      "logo": "https://img.stackshare.io/service/9681/27013154.png"
    },
    {
      "tool": "Docker Hub",
      "logo": "https://img.stackshare.io/service/3613/3SqWkwQA_400x400.png"
    },
    {
      "tool": "Amazon Pinpoint",
      "logo": "https://img.stackshare.io/service/6088/16ffae8c667bdbc6a4969f6f02090652.png"
    },
    {
      "tool": "XAMPP",
      "logo": "https://img.stackshare.io/service/1631/XAMPP_128.png"
    },
    {
      "tool": "BeautifulSoup",
      "logo": "https://img.stackshare.io/service/4037/no-img-open-source.png"
    },
    {
      "tool": "Squarespace",
      "logo": "https://img.stackshare.io/service/178/huJH2lyt_400x400.jpg"
    },
    {
      "tool": "PrimeFaces",
      "logo": "https://img.stackshare.io/service/4544/72csqYh2_400x400.jpg"
    },
    {
      "tool": "Google Cloud Datastore",
      "logo": "https://img.stackshare.io/service/2754/google_cloud_datastore.png"
    },
    {
      "tool": "Playwright",
      "logo": "https://img.stackshare.io/service/11955/no-img.png"
    },
    {
      "tool": "Airbrake",
      "logo": "https://img.stackshare.io/service/194/MCc1W3L8_400x400.jpg"
    },
    {
      "tool": "uWSGI",
      "logo": "https://img.stackshare.io/service/1838/uwsgi.png"
    },
    {
      "tool": "containerd",
      "logo": "https://img.stackshare.io/service/10053/containerd-icon.png"
    },
    {
      "tool": "Laravel Homestead",
      "logo": "https://img.stackshare.io/service/2001/74c5dd82a8b5540ab7dd4ce30fc0a2f6.png"
    },
    {
      "tool": "GitUI",
      "logo": "https://img.stackshare.io/service/12617/GitUI.png"
    },
    {
      "tool": "PostGraphile",
      "logo": "https://img.stackshare.io/service/4991/postgraphile.optimized.square.png"
    },
    {
      "tool": "Loggly",
      "logo": "https://img.stackshare.io/service/83/jy01f4p69n78p0nl4xou.png"
    },
    {
      "tool": "Kali Linux",
      "logo": "https://img.stackshare.io/service/5684/rYruOQvA_400x400.png"
    },
    {
      "tool": "Mac OS X",
      "logo": "https://img.stackshare.io/service/4369/iEqpsbUA_400x400.png"
    },
    {
      "tool": "Nodemailer",
      "logo": "https://img.stackshare.io/service/2862/qr2-jCLr.jpg"
    },
    {
      "tool": "MessageBird",
      "logo": "https://img.stackshare.io/service/3963/319915-3e31123c8391e49a0f03b69030a6b671-medium_jpg.jpg"
    },
    {
      "tool": "SocketCluster",
      "logo": "https://img.stackshare.io/service/3192/v2uoilfV.png"
    },
    {
      "tool": "Google Cloud CDN",
      "logo": "https://img.stackshare.io/service/4946/google-cloud-cdn.png"
    },
    {
      "tool": "Nextcloud",
      "logo": "https://img.stackshare.io/service/7679/DMp2TQox_400x400.jpg"
    },
    {
      "tool": "Red Hat Codeready Workspaces",
      "logo": "https://img.stackshare.io/service/198/unnamed.jpg"
    },
    {
      "tool": "Splunk Cloud",
      "logo": "https://img.stackshare.io/service/287/facebook-180-180.png"
    },
    {
      "tool": "Constant Contact",
      "logo": "https://img.stackshare.io/service/50/nFz-fG-v_400x400.jpg"
    },
    {
      "tool": "Redux Persist",
      "logo": "https://img.stackshare.io/service/6740/no-img-open-source.png"
    },
    {
      "tool": "Moleculer",
      "logo": "https://img.stackshare.io/service/7910/tDNHA1g1_400x400.jpg"
    },
    {
      "tool": "ArangoDB",
      "logo": "https://img.stackshare.io/service/1440/iFN2XAaA.png"
    },
    {
      "tool": "Dgraph",
      "logo": "https://img.stackshare.io/service/7071/MrEYkPFd_400x400.jpg"
    },
    {
      "tool": "Apache Kudu",
      "logo": "https://img.stackshare.io/service/3696/kudo.png"
    },
    {
      "tool": "Surge",
      "logo": "https://img.stackshare.io/service/3646/W-ShR64-.png"
    },
    {
      "tool": "Charles",
      "logo": "https://img.stackshare.io/service/2493/charles_icon.png"
    },
    {
      "tool": "AWS OpsWorks",
      "logo": "https://img.stackshare.io/service/419/aws-opswork.png"
    },
    {
      "tool": "Hangfire",
      "logo": "https://img.stackshare.io/service/4676/7880472.png"
    },
    {
      "tool": "8base",
      "logo": "https://img.stackshare.io/service/10131/8base_Logo.png"
    },
    {
      "tool": "Cyberduck",
      "logo": "https://img.stackshare.io/service/8176/tRZxSYUy_400x400.jpg"
    },
    {
      "tool": "Google Cloud Build",
      "logo": "https://img.stackshare.io/service/9309/PoHJY3K8_400x400.jpg"
    },
    {
      "tool": "Galen",
      "logo": "https://img.stackshare.io/service/6830/1c60d40a0ff18db9d5c11a93c35d7d49_400x400.png"
    },
    {
      "tool": "Shuup",
      "logo": "https://img.stackshare.io/service/11290/FBfy0f-b_400x400.jpg"
    },
    {
      "tool": "asyncio",
      "logo": "https://img.stackshare.io/service/4569/0_cOqooDOsnb8jDm2G.png"
    },
    {
      "tool": "Realm",
      "logo": "https://img.stackshare.io/service/1140/realm_logo_200_x_200.png"
    },
    {
      "tool": "RxDB",
      "logo": "https://img.stackshare.io/service/6950/EkEkGLtZ.jpg"
    },
    {
      "tool": "Cachet",
      "logo": "https://img.stackshare.io/service/2749/mH9IpOz7.png"
    },
    {
      "tool": "8base",
      "logo": "https://img.stackshare.io/service/10131/8base_Logo.png"
    },
    {
      "tool": "MessageBird",
      "logo": "https://img.stackshare.io/service/3963/319915-3e31123c8391e49a0f03b69030a6b671-medium_jpg.jpg"
    },
    {
      "tool": "Cachet",
      "logo": "https://img.stackshare.io/service/2749/mH9IpOz7.png"
    },
    {
      "tool": "AWS OpsWorks",
      "logo": "https://img.stackshare.io/service/419/aws-opswork.png"
    },
    {
      "tool": "Pouchdb",
      "logo": "https://img.stackshare.io/service/4114/_Bx4twqB.png"
    },
    {
      "tool": "Hangfire",
      "logo": "https://img.stackshare.io/service/4676/7880472.png"
    },
    {
      "tool": "Detox",
      "logo": "https://img.stackshare.io/service/8187/MfRcYRSi_400x400.jpg"
    },
    {
      "tool": "ProductPlan",
      "logo": "https://img.stackshare.io/service/1342/9f120f4a91796a880313b64bfcec6e15.jpeg"
    },
    {
      "tool": "JUCE",
      "logo": "https://img.stackshare.io/service/2793/dSXfOs9O_400x400.png"
    },
    {
      "tool": "Instana",
      "logo": "https://img.stackshare.io/service/9783/Nc8SewS2_400x400.jpg"
    },
    {
      "tool": "Zammad",
      "logo": "https://img.stackshare.io/service/6415/zammad.png"
    },
    {
      "tool": "Amazon Chime",
      "logo": "https://img.stackshare.io/service/6525/apple-icon-180x180.png"
    },
    {
      "tool": "Dyn",
      "logo": "https://img.stackshare.io/service/37/fsKWm_AI_400x400.jpg"
    },
    {
      "tool": "Amazon SimpleDB",
      "logo": "https://img.stackshare.io/service/403/amazon-simpledb.png"
    },
    {
      "tool": "Kairos API",
      "logo": "https://img.stackshare.io/service/834/A-AC8l1Z.png"
    },
    {
      "tool": "Amazon SWF",
      "logo": "https://img.stackshare.io/service/394/16ffae8c667bdbc6a4969f6f02090652.png"
    },
    {
      "tool": "BulkSMS",
      "logo": "https://img.stackshare.io/service/444/IXrUx-Zw.png"
    },
    {
      "tool": "ipapi",
      "logo": "https://img.stackshare.io/service/11686/icon-64.a33f449690cd.png"
    },
    {
      "tool": "Heroku CI",
      "logo": "https://img.stackshare.io/service/6945/heroku-ci.png"
    },
    {
      "tool": "NGINX Amplify",
      "logo": "https://img.stackshare.io/service/4180/dxGHt0g.png"
    },
    {
      "tool": "Azure CDN",
      "logo": "https://img.stackshare.io/service/5512/azure-cdn.png"
    },
    {
      "tool": "Morpheus",
      "logo": "https://img.stackshare.io/service/5761/7Iwug2lR.jpg"
    },
    {
      "tool": "Pact",
      "logo": "https://img.stackshare.io/service/11305/pact.png"
    },
    {
      "tool": "Dremio",
      "logo": "https://img.stackshare.io/service/9150/elaJVOma_400x400.jpg"
    },
    {
      "tool": "Spree",
      "logo": "https://img.stackshare.io/service/1098/6G46CP-7.png"
    },
    {
      "tool": "NServiceBus",
      "logo": "https://img.stackshare.io/service/2885/ENuT-Iy4_400x400.png"
    },
    {
      "tool": "VisualOps",
      "logo": "https://img.stackshare.io/service/828/fN_nQ9jI.png"
    },
    {
      "tool": "Errorception",
      "logo": "https://img.stackshare.io/service/590/Screen_shot_2011-08-01_at_3.30.19_AM.png"
    },
    {
      "tool": "Pact",
      "logo": "https://img.stackshare.io/service/11305/pact.png"
    },
    {
      "tool": "Dremio",
      "logo": "https://img.stackshare.io/service/9150/elaJVOma_400x400.jpg"
    },
    {
      "tool": "Launchaco",
      "logo": "https://img.stackshare.io/service/6114/ETU_kKY5.jpg"
    },
    {
      "tool": "AppScale",
      "logo": "https://img.stackshare.io/service/1242/G1n7aISg.jpeg"
    },
    {
      "tool": "Heroku CI",
      "logo": "https://img.stackshare.io/service/6945/heroku-ci.png"
    },
    {
      "tool": "BrowserSync",
      "logo": "https://img.stackshare.io/service/2600/c22Igh9q.png"
    },
    {
      "tool": "Framework7",
      "logo": "https://img.stackshare.io/service/2520/framework7.png"
    },
    {
      "tool": "Amazon SWF",
      "logo": "https://img.stackshare.io/service/394/16ffae8c667bdbc6a4969f6f02090652.png"
    },
    {
      "tool": "Vuesax",
      "logo": "https://img.stackshare.io/service/9114/vuesax-logo.png"
    },
    {
      "tool": "Dyn",
      "logo": "https://img.stackshare.io/service/37/fsKWm_AI_400x400.jpg"
    },
    {
      "tool": "BulkSMS",
      "logo": "https://img.stackshare.io/service/444/IXrUx-Zw.png"
    },
    {
      "tool": "Morpheus",
      "logo": "https://img.stackshare.io/service/5761/7Iwug2lR.jpg"
    },
    {
      "tool": "JUCE",
      "logo": "https://img.stackshare.io/service/2793/dSXfOs9O_400x400.png"
    },
    {
      "tool": "Domino",
      "logo": "https://img.stackshare.io/service/1133/c295ea015debc091e92ed099f111413b.png"
    },
    {
      "tool": "Cloudcraft",
      "logo": "https://img.stackshare.io/service/3912/cloudcraft.png"
    },
    {
      "tool": "MaxCDN",
      "logo": "https://img.stackshare.io/service/14/HG2q2Oxj.png"
    },
    {
      "tool": "Amazon Chime",
      "logo": "https://img.stackshare.io/service/6525/apple-icon-180x180.png"
    },
    {
      "tool": "Passbolt",
      "logo": "https://img.stackshare.io/service/4992/fxjngQyJ.jpg"
    },
    {
      "tool": "Spree",
      "logo": "https://img.stackshare.io/service/1098/6G46CP-7.png"
    },
    {
      "tool": "Twisted",
      "logo": "https://img.stackshare.io/service/5383/791b2231ab1c789830e8a6bd0fdb50f5.png"
    },
    {
      "tool": "Nevercode",
      "logo": "https://img.stackshare.io/service/7059/86XUqq54_400x400.jpg"
    },
    {
      "tool": "Hug",
      "logo": "https://img.stackshare.io/service/4608/hug.png"
    },
    {
      "tool": "Perforce",
      "logo": "https://img.stackshare.io/service/2119/Helix_Core_logo.png"
    },
    {
      "tool": "MaxCDN",
      "logo": "https://img.stackshare.io/service/14/HG2q2Oxj.png"
    },
    {
      "tool": "Amazon Chime",
      "logo": "https://img.stackshare.io/service/6525/apple-icon-180x180.png"
    },
    {
      "tool": "Morpheus",
      "logo": "https://img.stackshare.io/service/5761/7Iwug2lR.jpg"
    },
    {
      "tool": "Cloudcraft",
      "logo": "https://img.stackshare.io/service/3912/cloudcraft.png"
    },
    {
      "tool": "CodeRunner",
      "logo": "https://img.stackshare.io/service/8344/New_Project__63_.png"
    },
    {
      "tool": "Amazon EBS",
      "logo": "https://img.stackshare.io/service/231/amazon-ebs.png"
    },
    {
      "tool": "Hug",
      "logo": "https://img.stackshare.io/service/4608/hug.png"
    },
    {
      "tool": "Launchaco",
      "logo": "https://img.stackshare.io/service/6114/ETU_kKY5.jpg"
    },
    {
      "tool": "kops",
      "logo": "https://img.stackshare.io/service/7643/kops-logo.jpg"
    },
    {
      "tool": "Slim Lang",
      "logo": "https://img.stackshare.io/service/3267/3170032.png"
    },
    {
      "tool": "Underscore",
      "logo": "https://img.stackshare.io/service/1150/underscore-js.png"
    },
    {
      "tool": "Twisted",
      "logo": "https://img.stackshare.io/service/5383/791b2231ab1c789830e8a6bd0fdb50f5.png"
    },
    {
      "tool": "Amazon Glacier",
      "logo": "https://img.stackshare.io/service/387/amazon-glacier.png"
    },
    {
      "tool": "Nevercode",
      "logo": "https://img.stackshare.io/service/7059/86XUqq54_400x400.jpg"
    },
    {
      "tool": "Instana",
      "logo": "https://img.stackshare.io/service/9783/Nc8SewS2_400x400.jpg"
    },
    {
      "tool": "drf-yasg",
      "logo": "https://img.stackshare.io/service/12444/no-img.png"
    },
    {
      "tool": "Theia",
      "logo": "https://img.stackshare.io/service/7263/28530323.png"
    },
    {
      "tool": "Plastic SCM",
      "logo": "https://img.stackshare.io/service/3809/logo-semanticmerge-squared.png"
    },
    {
      "tool": "VelocityDB",
      "logo": "https://img.stackshare.io/service/4759/New_Project__16_.jpg"
    },
    {
      "tool": "Vala",
      "logo": "https://img.stackshare.io/service/4409/no-img-open-source.png"
    },
    {
      "tool": "Unicons",
      "logo": "https://img.stackshare.io/service/11857/unicons.png"
    },
    {
      "tool": "HireFire",
      "logo": "https://img.stackshare.io/service/9994/dwQR9YHl_400x400.jpg"
    },
    {
      "tool": "Web3j",
      "logo": "https://img.stackshare.io/service/11569/web3j.png"
    },
    {
      "tool": "DreamHost",
      "logo": "https://img.stackshare.io/service/2218/rdBxld5i_400x400.png"
    },
    {
      "tool": "DuckDB",
      "logo": "https://img.stackshare.io/service/12279/zyPbZWCb_400x400.png"
    },
    {
      "tool": "HireFire",
      "logo": "https://img.stackshare.io/service/9994/dwQR9YHl_400x400.jpg"
    },
    {
      "tool": "Web3j",
      "logo": "https://img.stackshare.io/service/11569/web3j.png"
    },
    {
      "tool": "Salesforce",
      "logo": "https://img.stackshare.io/service/12695/D78-IV9i_400x400.jpg"
    },
    {
      "tool": "Autocode IDE",
      "logo": "https://img.stackshare.io/service/11793/autocode.png"
    },
    {
      "tool": "Security Reviewer",
      "logo": "https://img.stackshare.io/service/11422/0.png"
    },
    {
      "tool": "Spatium Wallet",
      "logo": "https://img.stackshare.io/service/12412/2Gz9Kxnc_400x400.jpg"
    },
    {
      "tool": "Rekognition API",
      "logo": "https://img.stackshare.io/service/863/dt6R8yoD.jpeg"
    },
    {
      "tool": "Gmail",
      "logo": "https://img.stackshare.io/service/3167/_K34MGL8_400x400.jpg"
    },
    {
      "tool": "Stack Overflow",
      "logo": "https://img.stackshare.io/service/1927/so-icon.png"
    },
    {
      "tool": "Ubuntu",
      "logo": "https://img.stackshare.io/service/3511/cof_orange_hex.jpg"
    },
    {
      "tool": "TypeScript",
      "logo": "https://img.stackshare.io/service/1612/bynNY5dJ.jpg"
    },
    {
      "tool": "Vue.js",
      "logo": "https://img.stackshare.io/service/3837/paeckCWC.png"
    },
    {
      "tool": "Sass",
      "logo": "https://img.stackshare.io/service/1171/jCR2zNJV.png"
    },
    {
      "tool": "Google Maps",
      "logo": "https://img.stackshare.io/service/1652/googlemaps.png"
    },
    {
      "tool": "PyCharm",
      "logo": "https://img.stackshare.io/service/1644/logo.png"
    },
    {
      "tool": "Font Awesome",
      "logo": "https://img.stackshare.io/service/3244/1_Mr1Fy00XjPGNf1Kkp_hWtw_2x.png"
    },
    {
      "tool": "G Suite",
      "logo": "https://img.stackshare.io/service/247/oYkAxyQM_400x400.jpg"
    },
    {
      "tool": "Android SDK",
      "logo": "https://img.stackshare.io/service/1010/m8jf0po4imu8t5eemjdd.png"
    },
    {
      "tool": "Microsoft SQL Server",
      "logo": "https://img.stackshare.io/service/1027/sql_server.png"
    },
    {
      "tool": "Markdown",
      "logo": "https://img.stackshare.io/service/1147/markdown.png"
    },
    {
      "tool": "Notepad++",
      "logo": "https://img.stackshare.io/service/646/logo.png"
    },
    {
      "tool": "Google Cloud Platform",
      "logo": "https://img.stackshare.io/service/4240/1a61e4pu_400x400.jpg"
    },
    {
      "tool": "PayPal",
      "logo": "https://img.stackshare.io/service/236/yy3lVE1y.jpeg"
    },
    {
      "tool": "Google Fonts",
      "logo": "https://img.stackshare.io/service/2652/ZWREQYdH_400x400.jpg"
    },
    {
      "tool": "Flask",
      "logo": "https://img.stackshare.io/service/1001/flask.jpg"
    },
    {
      "tool": "ASP.NET",
      "logo": "https://img.stackshare.io/service/6755/2c45151a4a11d3a3c8e71bb34dd069d6_400x400.png"
    },
    {
      "tool": "Skype",
      "logo": "https://img.stackshare.io/service/340/skype.png"
    },
    {
      "tool": "Stripe",
      "logo": "https://img.stackshare.io/service/97/eW6tXeq3.png"
    },
    {
      "tool": "Swift",
      "logo": "https://img.stackshare.io/service/1009/tuHsaI2U.png"
    },
    {
      "tool": "jQuery UI",
      "logo": "https://img.stackshare.io/service/1022/jqueryui_avatar_96.png"
    },
    {
      "tool": "Apache Tomcat",
      "logo": "https://img.stackshare.io/service/1187/tomcat.png"
    },
    {
      "tool": "Babel",
      "logo": "https://img.stackshare.io/service/2739/-1wfGjNw.png"
    },
    {
      "tool": "MariaDB",
      "logo": "https://img.stackshare.io/service/1615/mariadb-logo-400x400.png"
    },
    {
      "tool": "Rails",
      "logo": "https://img.stackshare.io/service/990/x57_Lorv.png"
    },
    {
      "tool": "AWS Elastic Load Balancing ...",
      "logo": "https://img.stackshare.io/service/2587/aws-elastic-load-balancing.png"
    },
    {
      "tool": "CentOS",
      "logo": "https://img.stackshare.io/service/3069/PBnd8yDL_400x400.jpg"
    },
    {
      "tool": "Amazon CloudFront",
      "logo": "https://img.stackshare.io/service/13/amazon-cloudfront.png"
    },
    {
      "tool": "Material Design for Angular",
      "logo": "https://img.stackshare.io/service/1523/square.png"
    },
    {
      "tool": "OpenSSL",
      "logo": "https://img.stackshare.io/service/3091/preview.png"
    },
    {
      "tool": "Google Tag Manager",
      "logo": "https://img.stackshare.io/service/2107/googleTagManager.png"
    },
    {
      "tool": "Google Compute Engine",
      "logo": "https://img.stackshare.io/service/518/s01TMTGn.png"
    },
    {
      "tool": "Debian",
      "logo": "https://img.stackshare.io/service/1656/vd4gAekh.png"
    },
    {
      "tool": "Logstash",
      "logo": "https://img.stackshare.io/service/1683/preview.png"
    },
    {
      "tool": "Gradle",
      "logo": "https://img.stackshare.io/service/975/gradlephant-social-black-bg.png"
    },
    {
      "tool": "Amazon CloudWatch",
      "logo": "https://img.stackshare.io/service/401/amazon-cloudwatch.png"
    },
    {
      "tool": "PhpStorm",
      "logo": "https://img.stackshare.io/service/1452/icon_PhpStorm.png"
    },
    {
      "tool": "Twilio",
      "logo": "https://img.stackshare.io/service/130/VrwpNfjh_400x400.png"
    },
    {
      "tool": "Scala",
      "logo": "https://img.stackshare.io/service/1012/scala.png"
    },
    {
      "tool": "Google App Engine",
      "logo": "https://img.stackshare.io/service/139/s01TMTGn.png"
    },
    {
      "tool": "gulp",
      "logo": "https://img.stackshare.io/service/844/iruTC031.png"
    },
    {
      "tool": "CircleCI",
      "logo": "https://img.stackshare.io/service/190/CvqrSSFs_400x400.jpg"
    },
    {
      "tool": "Electron",
      "logo": "https://img.stackshare.io/service/2946/XJRdVxx3.png"
    },
    {
      "tool": "WooCommerce",
      "logo": "https://img.stackshare.io/service/3139/y2hg0gx5_400x400.jpg"
    },
    {
      "tool": "HubSpot",
      "logo": "https://img.stackshare.io/service/256/9Q0oQwl2_400x400.jpg"
    },
    {
      "tool": "InVision",
      "logo": "https://img.stackshare.io/service/165/r9uL4jWU.png"
    },
    {
      "tool": "Travis CI",
      "logo": "https://img.stackshare.io/service/460/Lu6cGu0z_400x400.png"
    },
    {
      "tool": "Flutter",
      "logo": "https://img.stackshare.io/service/7180/flutter-mark-square-100.png"
    },
    {
      "tool": "Amazon SES",
      "logo": "https://img.stackshare.io/service/17/amazon-ses.png"
    },
    {
      "tool": "Twilio SendGrid",
      "logo": "https://img.stackshare.io/service/43/kQ_6nwmP.jpg"
    },
    {
      "tool": "Objective-C",
      "logo": "https://img.stackshare.io/service/1008/xcode.png"
    },
    {
      "tool": "Kotlin",
      "logo": "https://img.stackshare.io/service/3750/pCfEzr6L.png"
    },
    {
      "tool": "Angular 2",
      "logo": "https://img.stackshare.io/service/3745/cb8U-gL6_400x400.jpg"
    },
    {
      "tool": "Intercom",
      "logo": "https://img.stackshare.io/service/257/qmwr6vjg_400x400.png"
    },
    {
      "tool": "Mailgun",
      "logo": "https://img.stackshare.io/service/44/ICON_MAILGUN_NOFX.png"
    },
    {
      "tool": "ASP.NET Core",
      "logo": "https://img.stackshare.io/service/11331/asp.net-core.png"
    },
    {
      "tool": "Drupal",
      "logo": "https://img.stackshare.io/service/1226/H9IAAYru_400x400.jpg"
    },
    {
      "tool": "Handlebars.js",
      "logo": "https://img.stackshare.io/service/1143/Handlebars.png"
    },
    {
      "tool": ".NET Core",
      "logo": "https://img.stackshare.io/service/6403/9141961.png"
    },
    {
      "tool": "Apache Spark",
      "logo": "https://img.stackshare.io/service/2220/ca72c4715da998b0bf5d1c857958bed3.png"
    },
    {
      "tool": "Animate.css",
      "logo": "https://img.stackshare.io/service/9195/animate-css.png"
    },
    {
      "tool": "RequireJS",
      "logo": "https://img.stackshare.io/service/852/1781835.png"
    },
    {
      "tool": "Bower",
      "logo": "https://img.stackshare.io/service/847/66db62603f426a8fc6664081811be6d4.png"
    },
    {
      "tool": "AddThis",
      "logo": "https://img.stackshare.io/service/3421/T3VyOpzk_400x400.png"
    },
    {
      "tool": "Azure DevOps",
      "logo": "https://img.stackshare.io/service/4313/XNKktHjN_400x400.png"
    },
    {
      "tool": "Microsoft Teams",
      "logo": "https://img.stackshare.io/service/5989/teams.png"
    },
    {
      "tool": "Prometheus",
      "logo": "https://img.stackshare.io/service/2501/prometheus.png"
    },
    {
      "tool": "notion.so",
      "logo": "https://img.stackshare.io/service/6758/cbCR7w5R_400x400.jpg"
    },
    {
      "tool": "Apollo",
      "logo": "https://img.stackshare.io/service/5508/CyUH653y.png"
    },
    {
      "tool": "Backbone.js",
      "logo": "https://img.stackshare.io/service/1017/Screen_Shot_2012-04-28_at_8.52.15_PM.png"
    },
    {
      "tool": "Prettier",
      "logo": "https://img.stackshare.io/service/7035/icon.png"
    },
    {
      "tool": "JSON",
      "logo": "https://img.stackshare.io/service/2880/1024px-JSON_vector_logo.svg.png"
    },
    {
      "tool": "Netlify",
      "logo": "https://img.stackshare.io/service/2748/lV55uZMx.png"
    },
    {
      "tool": "Spring",
      "logo": "https://img.stackshare.io/service/996/unnamed.jpg"
    },
    {
      "tool": "Airflow",
      "logo": "https://img.stackshare.io/service/3130/airflow.png"
    },
    {
      "tool": "Elixir",
      "logo": "https://img.stackshare.io/service/1974/drop.png"
    },
    {
      "tool": "GitLab CI",
      "logo": "https://img.stackshare.io/service/5545/9pAwHBR0.jpg"
    },
    {
      "tool": "Adobe XD",
      "logo": "https://img.stackshare.io/service/5602/adobe-xd-logo.png"
    },
    {
      "tool": "axios",
      "logo": "https://img.stackshare.io/no-img-open-source.png"
    },
    {
      "tool": "Adobe Photoshop",
      "logo": "https://img.stackshare.io/service/3176/lxVcZyci.jpg"
    },
    {
      "tool": "Zoom",
      "logo": "https://img.stackshare.io/service/6083/oD_oPSBP_400x400.jpg"
    },
    {
      "tool": "Microsoft Office 365",
      "logo": "https://img.stackshare.io/service/4167/icon.png"
    },
    {
      "tool": "R Language",
      "logo": "https://img.stackshare.io/service/1213/r-logo.png"
    },
    {
      "tool": "iOS",
      "logo": "https://img.stackshare.io/service/2886/ios-logo.png"
    },
    {
      "tool": "Apache Maven",
      "logo": "https://img.stackshare.io/service/977/maven.png"
    },
    {
      "tool": "Slick",
      "logo": "https://img.stackshare.io/service/1843/slick.png"
    },
    {
      "tool": "vuex",
      "logo": "https://img.stackshare.io/service/6705/6128107.png"
    },
    {
      "tool": "Pandas",
      "logo": "https://img.stackshare.io/service/2180/1284191.png"
    },
    {
      "tool": "Nuxt.js",
      "logo": "https://img.stackshare.io/service/7304/23360933.png"
    },
    {
      "tool": "Hadoop",
      "logo": "https://img.stackshare.io/service/1044/elephant_rgb_sq.png"
    },
    {
      "tool": "PowerShell",
      "logo": "https://img.stackshare.io/service/3681/powershell-logo.png"
    },
    {
      "tool": "React Router",
      "logo": "https://img.stackshare.io/service/3350/8261421.png"
    },
    {
      "tool": "Keycloak",
      "logo": "https://img.stackshare.io/service/5439/oAC05cEB_400x400.png"
    },
    {
      "tool": "GitHub Actions",
      "logo": "https://img.stackshare.io/service/11563/actions.png"
    },
    {
      "tool": "Traefik",
      "logo": "https://img.stackshare.io/service/5126/soSblPVT_400x400.jpg"
    },
    {
      "tool": "Amazon Redshift",
      "logo": "https://img.stackshare.io/service/386/amazon-redshift.png"
    },
    {
      "tool": "React Redux",
      "logo": "https://img.stackshare.io/service/7374/react-redux.png"
    },
    {
      "tool": "Helm",
      "logo": "https://img.stackshare.io/service/5983/AHcBc6EG_400x400.jpg"
    },
    {
      "tool": "Cassandra",
      "logo": "https://img.stackshare.io/service/1032/cassandra_small.png"
    },
    {
      "tool": "ELK",
      "logo": "https://img.stackshare.io/service/1883/EmPbn9P0_400x400.png"
    },
    {
      "tool": "Adobe Illustrator",
      "logo": "https://img.stackshare.io/service/3175/adobe-illustrator.png"
    },
    {
      "tool": "Keras",
      "logo": "https://img.stackshare.io/service/5601/keras.png"
    },
    {
      "tool": "Svelte",
      "logo": "https://img.stackshare.io/service/6113/7exmJEg4_400x400.png"
    },
    {
      "tool": "styled-components",
      "logo": "https://img.stackshare.io/service/6749/styled-components.png"
    },
    {
      "tool": "Google BigQuery",
      "logo": "https://img.stackshare.io/service/695/BigQuery.png"
    },
    {
      "tool": "Neo4j",
      "logo": "https://img.stackshare.io/service/1482/FbkjM42a.png"
    },
    {
      "tool": "Angular CLI",
      "logo": "https://img.stackshare.io/service/5527/9kVhSQ9y_400x400.jpg"
    },
    {
      "tool": "Oracle",
      "logo": "https://img.stackshare.io/service/1026/jT-HJYJg.png"
    },
    {
      "tool": "Serverless",
      "logo": "https://img.stackshare.io/service/5095/serverless-logo.png"
    },
    {
      "tool": "Salesforce Sales Cloud",
      "logo": "https://img.stackshare.io/service/35/lGZFUPOW.png"
    },
    {
      "tool": "Power BI",
      "logo": "https://img.stackshare.io/service/4166/m1mSM9Qf_400x400.jpg"
    },
    {
      "tool": "Amazon EKS",
      "logo": "https://img.stackshare.io/service/7991/amazon-eks.png"
    },
    {
      "tool": "Angular Material",
      "logo": "https://img.stackshare.io/service/5445/cb8U-gL6_400x400.jpg"
    },
    {
      "tool": "Arduino",
      "logo": "https://img.stackshare.io/service/3195/9d19310763171b0d958d23a18b3d7e1c.png"
    },
    {
      "tool": "JUnit",
      "logo": "https://img.stackshare.io/service/2020/874086.png"
    },
    {
      "tool": "Oracle PL/SQL",
      "logo": "https://img.stackshare.io/service/7328/plsql.png"
    },
    {
      "tool": "Eclipse",
      "logo": "https://img.stackshare.io/service/1446/8cyY6D_m.png"
    },
    {
      "tool": "Zapier",
      "logo": "https://img.stackshare.io/service/286/0bd8e9aaccec949490082ad22c7ee60f.png"
    },
    {
      "tool": "Angular Material",
      "logo": "https://img.stackshare.io/service/5445/cb8U-gL6_400x400.jpg"
    },
    {
      "tool": "AWS IAM",
      "logo": "https://img.stackshare.io/service/418/aws-iam.png"
    },
    {
      "tool": "JUnit",
      "logo": "https://img.stackshare.io/service/2020/874086.png"
    },
    {
      "tool": "Tailwind CSS",
      "logo": "https://img.stackshare.io/service/8158/E1G1nNb0_400x400.jpg"
    },
    {
      "tool": "Leaflet",
      "logo": "https://img.stackshare.io/service/2392/leaflet_upic.png"
    },
    {
      "tool": "Cloud Firestore",
      "logo": "https://img.stackshare.io/service/7696/Untitled-5.png"
    },
    {
      "tool": "Snowflake",
      "logo": "https://img.stackshare.io/service/5889/QYHZHC4n_400x400.png"
    },
    {
      "tool": "Simple",
      "logo": "https://img.stackshare.io/service/11894/simple.png"
    },
    {
      "tool": "Mocha",
      "logo": "https://img.stackshare.io/service/832/mocha.png"
    },
    {
      "tool": "AWS CloudFormation",
      "logo": "https://img.stackshare.io/service/411/aws-cloudformation.png"
    },
    {
      "tool": "GNU Bash",
      "logo": "https://img.stackshare.io/service/1673/bash-icon.png"
    },
    {
      "tool": "JetBrains Rider",
      "logo": "https://img.stackshare.io/service/7410/lh1l265w_400x400.jpg"
    },
    {
      "tool": "Miro",
      "logo": "https://img.stackshare.io/service/10825/1MYeZHg9_400x400.png"
    },
    {
      "tool": "OAuth2",
      "logo": "https://img.stackshare.io/service/4507/oauth2-logo.png"
    },
    {
      "tool": "Azure Functions",
      "logo": "https://img.stackshare.io/service/4851/functionlogo.jpg"
    },
    {
      "tool": "Airtable",
      "logo": "https://img.stackshare.io/service/1512/logo.png"
    },
    {
      "tool": "Zeplin",
      "logo": "https://img.stackshare.io/service/3457/SNbLveBx.jpg"
    },
    {
      "tool": "Cucumber",
      "logo": "https://img.stackshare.io/service/2544/jasVAxyJ.png"
    },
    {
      "tool": "nodemon",
      "logo": "https://img.stackshare.io/service/5577/preview.png"
    },
    {
      "tool": "gRPC",
      "logo": "https://img.stackshare.io/service/4670/Tb-g6Nu3_400x400.jpg"
    },
    {
      "tool": "Hugo",
      "logo": "https://img.stackshare.io/service/1158/hugo-icon.png"
    },
    {
      "tool": "Rancher",
      "logo": "https://img.stackshare.io/service/2552/rancher.png"
    },
    {
      "tool": "Airtable",
      "logo": "https://img.stackshare.io/service/1512/logo.png"
    },
    {
      "tool": "Rancher",
      "logo": "https://img.stackshare.io/service/2552/rancher.png"
    },
    {
      "tool": "Clojure",
      "logo": "https://img.stackshare.io/service/1003/Clojure_300x300.png"
    },
    {
      "tool": "Segment",
      "logo": "https://img.stackshare.io/service/5/x9miwEug_400x400.png"
    },
    {
      "tool": "Azure Cosmos DB",
      "logo": "https://img.stackshare.io/service/1369/nquiptD9.png"
    },
    {
      "tool": "Insomnia REST Client",
      "logo": "https://img.stackshare.io/service/6406/qLPJL1NZ.jpg"
    },
    {
      "tool": "Google Meet",
      "logo": "https://img.stackshare.io/service/8683/246x0w.jpg"
    },
    {
      "tool": "VMware vSphere",
      "logo": "https://img.stackshare.io/service/775/c193cd4e31d488620bdd7349ea4836cc.png"
    },
    {
      "tool": "WhatsApp",
      "logo": "https://img.stackshare.io/service/4410/SqyiYHRL_400x400.png"
    },
    {
      "tool": "RSpec",
      "logo": "https://img.stackshare.io/service/2539/logo.png"
    },
    {
      "tool": "Create React App",
      "logo": "https://img.stackshare.io/service/5537/oi64YzXY.jpg"
    },
    {
      "tool": "OpenCV",
      "logo": "https://img.stackshare.io/service/1293/opencv-logo-64x64.png"
    },
    {
      "tool": "Graylog",
      "logo": "https://img.stackshare.io/service/4392/_HU28D42.png"
    },
    {
      "tool": "Meteor",
      "logo": "https://img.stackshare.io/service/1162/uJPMDhZq.png"
    },
    {
      "tool": "PowerBI",
      "logo": "https://img.stackshare.io/service/3900/UvG4ZtYW_400x400.png"
    },
    {
      "tool": "ClickUp",
      "logo": "https://img.stackshare.io/service/9192/dSV8FSuF_400x400.png"
    },
    {
      "tool": "Swagger UI",
      "logo": "https://img.stackshare.io/service/3417/pIea9Ji0.png"
    },
    {
      "tool": "Lodash",
      "logo": "https://img.stackshare.io/service/2438/lodash.png"
    },
    {
      "tool": "Let's Encrypt",
      "logo": "https://img.stackshare.io/service/4225/lSuJvwXU_400x400.jpg"
    },
    {
      "tool": "Emacs",
      "logo": "https://img.stackshare.io/service/645/emacs.gif"
    },
    {
      "tool": "Firebase Authentication",
      "logo": "https://img.stackshare.io/service/9155/unnamed.jpg"
    },
    {
      "tool": "Microsoft Excel",
      "logo": "https://img.stackshare.io/service/5279/RZPZ1KYT_400x400.png"
    },
    {
      "tool": "GoLand",
      "logo": "https://img.stackshare.io/service/8004/CZjD2GYK_400x400.jpg"
    },
    {
      "tool": "Angular Universal",
      "logo": "https://img.stackshare.io/service/6665/cb8U-gL6_400x400.jpg"
    },
    {
      "tool": "Fluentd",
      "logo": "https://img.stackshare.io/service/4365/859518.png"
    },
    {
      "tool": "Lodash",
      "logo": "https://img.stackshare.io/service/2438/lodash.png"
    },
    {
      "tool": "Groovy",
      "logo": "https://img.stackshare.io/service/997/6d180ca6647e7f690c2615a86e7c2843.png"
    },
    {
      "tool": "Ember.js",
      "logo": "https://img.stackshare.io/service/1018/3s1seyc0csl75btyw1vl.png"
    },
    {
      "tool": "Red Hat OpenShift",
      "logo": "https://img.stackshare.io/service/197/854d85d0c77271af224b455f81b5fc88.png"
    },
    {
      "tool": "Let's Encrypt",
      "logo": "https://img.stackshare.io/service/4225/lSuJvwXU_400x400.jpg"
    },
    {
      "tool": "Google Sheets",
      "logo": "https://img.stackshare.io/service/1100/google-sheets.jpg"
    },
    {
      "tool": "Spring Security",
      "logo": "https://img.stackshare.io/service/6656/com.castsoftware.springsecurity.png"
    },
    {
      "tool": "GoLand",
      "logo": "https://img.stackshare.io/service/8004/CZjD2GYK_400x400.jpg"
    },
    {
      "tool": "Microsoft Excel",
      "logo": "https://img.stackshare.io/service/5279/RZPZ1KYT_400x400.png"
    },
    {
      "tool": "AWS Glue",
      "logo": "https://img.stackshare.io/service/8906/AWS-Glue_4x.png"
    },
    {
      "tool": "Storybook",
      "logo": "https://img.stackshare.io/service/9240/sOct-Txm_400x400.png"
    },
    {
      "tool": "Akka",
      "logo": "https://img.stackshare.io/service/1773/bxLhidly.png"
    },
    {
      "tool": "Microsoft SQL Server Manage...",
      "logo": "https://img.stackshare.io/service/7096/809746be-0b96-4af0-aa2f-5d1aeaa82658.png"
    },
    {
      "tool": "SQLAlchemy",
      "logo": "https://img.stackshare.io/service/1839/q5uAkmy7.png"
    },
    {
      "tool": "Facebook Ads",
      "logo": "https://img.stackshare.io/service/5144/X4G0h2LY_400x400.png"
    },
    {
      "tool": "TeamCity",
      "logo": "https://img.stackshare.io/service/1357/317jQkeS.png"
    },
    {
      "tool": "Redmine",
      "logo": "https://img.stackshare.io/service/1186/redmine-logo-twitter_400x400.png"
    },
    {
      "tool": "cnvrg.io",
      "logo": "https://img.stackshare.io/service/12607/urChdCLm_400x400.jpg"
    },
    {
      "tool": "Istio",
      "logo": "https://img.stackshare.io/service/7028/AGpa5VZV.jpg"
    },
    {
      "tool": "Argo",
      "logo": "https://img.stackshare.io/service/9840/PqKLmP_S_400x400.jpg"
    },
    {
      "tool": "Android OS",
      "logo": "https://img.stackshare.io/service/9586/ZvmtaSXW_400x400.jpg"
    },
    {
      "tool": "Clickhouse",
      "logo": "https://img.stackshare.io/service/5725/cloickhouse.png"
    },
    {
      "tool": "D3.js",
      "logo": "https://img.stackshare.io/service/1491/HgKolWB5_400x400.jpg"
    },
    {
      "tool": "Azure Kubernetes Service",
      "logo": "https://img.stackshare.io/service/9133/Azure-Container-Service_COLOR-300x300.png"
    },
    {
      "tool": "MATLAB",
      "logo": "https://img.stackshare.io/service/1214/h5g3etjnacmazg8oq17z.jpeg"
    },
    {
      "tool": "MATLAB",
      "logo": "https://img.stackshare.io/service/1214/h5g3etjnacmazg8oq17z.jpeg"
    },
    {
      "tool": "cnvrg.io",
      "logo": "https://img.stackshare.io/service/12607/urChdCLm_400x400.jpg"
    },
    {
      "tool": "Azure Kubernetes Service",
      "logo": "https://img.stackshare.io/service/9133/Azure-Container-Service_COLOR-300x300.png"
    },
    {
      "tool": "TSLint",
      "logo": "https://img.stackshare.io/service/5561/303157.png"
    },
    {
      "tool": "SwiftUI",
      "logo": "https://img.stackshare.io/service/11099/swiftui.png"
    },
    {
      "tool": "Sonatype Nexus",
      "logo": "https://img.stackshare.io/service/1847/jnJFp3i1_400x400.jpg"
    },
    {
      "tool": "Entity Framework Core",
      "logo": "https://img.stackshare.io/service/10254/no-img-open-source.png"
    },
    {
      "tool": "Sequelize",
      "logo": "https://img.stackshare.io/service/3211/3591786.png"
    },
    {
      "tool": "Windows 10",
      "logo": "https://img.stackshare.io/service/7205/U54M_YbJ_400x400.jpg"
    },
    {
      "tool": "SignalR",
      "logo": "https://img.stackshare.io/service/4013/SignalR-logo.png"
    },
    {
      "tool": "monday.com",
      "logo": "https://img.stackshare.io/service/9761/monday_logo_icon.png"
    },
    {
      "tool": "Amazon Elasticsearch Service",
      "logo": "https://img.stackshare.io/service/3736/amazon-elasticsearch-service.png"
    },
    {
      "tool": "DataGrip",
      "logo": "https://img.stackshare.io/service/5053/datagrip-logo.png"
    },
    {
      "tool": "Robot Framework",
      "logo": "https://img.stackshare.io/service/4092/QdWJdB_g_400x400.jpg"
    },
    {
      "tool": "Consul",
      "logo": "https://img.stackshare.io/service/747/consul-logo-grad_teaser.png"
    },
    {
      "tool": "Composer",
      "logo": "https://img.stackshare.io/service/1688/New_Project__65_.png"
    },
    {
      "tool": "RStudio",
      "logo": "https://img.stackshare.io/service/2382/YYMiHBTH_400x400.png"
    },
    {
      "tool": "Mapbox",
      "logo": "https://img.stackshare.io/service/1640/cvosutVr_400x400.jpg"
    },
    {
      "tool": "NumPy",
      "logo": "https://img.stackshare.io/service/2179/preview.jpeg"
    },
    {
      "tool": "Matplotlib",
      "logo": "https://img.stackshare.io/service/2993/2DZC4KaA_400x400.jpg"
    },
    {
      "tool": "AWS Fargate",
      "logo": "https://img.stackshare.io/service/7969/aws-fargate.jpg"
    },
    {
      "tool": "OpenAPI",
      "logo": "https://img.stackshare.io/service/9792/L8C2-2bd_400x400.jpg"
    },
    {
      "tool": "H2 Database",
      "logo": "https://img.stackshare.io/service/3105/h2-logo_square_400x400.png"
    },
    {
      "tool": "RxJS",
      "logo": "https://img.stackshare.io/service/1796/984368.png"
    },
    {
      "tool": "JSON Web Token",
      "logo": "https://img.stackshare.io/service/6417/jwt-icon.png"
    },
    {
      "tool": "SignalR",
      "logo": "https://img.stackshare.io/service/4013/SignalR-logo.png"
    },
    {
      "tool": "DB",
      "logo": "https://img.stackshare.io/service/11593/no-img.png"
    },
    {
      "tool": "Lucidchart",
      "logo": "https://img.stackshare.io/service/4223/lucidchart-06-535x535.png"
    },
    {
      "tool": "Google Kubernetes Engine",
      "logo": "https://img.stackshare.io/service/1587/s01TMTGn.png"
    },
    {
      "tool": "Spark NLP",
      "logo": "https://img.stackshare.io/service/12514/small.png"
    },
    {
      "tool": "Data Studio",
      "logo": "https://img.stackshare.io/service/5339/PSpUS-Hp_400x400.jpg"
    },
    {
      "tool": "Kafka Streams",
      "logo": "https://img.stackshare.io/service/9190/kazUJooF_400x400.jpg"
    },
    {
      "tool": "TestNG",
      "logo": "https://img.stackshare.io/service/8900/no-img-open-source.png"
    },
    {
      "tool": "Anaconda",
      "logo": "https://img.stackshare.io/service/4168/vB6sRNsh_400x400.jpg"
    },
    {
      "tool": "Caddy",
      "logo": "https://img.stackshare.io/service/3834/caddy.png"
    },
    {
      "tool": "Raspberry Pi",
      "logo": "https://img.stackshare.io/service/5174/LcSgue9p_400x400.png"
    },
    {
      "tool": "Kong",
      "logo": "https://ucarecdn.com/3cf09daa-4e1e-404e-a612-f8a91c661db2/"
    },
    {
      "tool": "MobX",
      "logo": "https://img.stackshare.io/service/5302/17475736.png"
    },
    {
      "tool": "Amazon RDS for Aurora",
      "logo": "https://img.stackshare.io/service/1924/amazon-rds.png"
    },
    {
      "tool": "Percy",
      "logo": "https://img.stackshare.io/service/9635/ZLa0MjPw_400x400.jpg"
    },
    {
      "tool": "Jekyll",
      "logo": "https://img.stackshare.io/service/1114/ad968c1615d956e800fa36494314f48c.jpeg"
    },
    {
      "tool": "Salesforce Marketing Cloud",
      "logo": "https://img.stackshare.io/service/8520/mVUDo78h_400x400.jpg"
    },
    {
      "tool": "Codecov",
      "logo": "https://img.stackshare.io/service/2673/Codecov_Mark_Circle_Pink.png"
    },
    {
      "tool": "Firebase Hosting",
      "logo": "https://img.stackshare.io/service/6688/m3cEA33V_400x400.jpg"
    },
    {
      "tool": "Zabbix",
      "logo": "https://img.stackshare.io/service/1705/MlkWTc_x.png"
    },
    {
      "tool": "Quasar Framework",
      "logo": "https://img.stackshare.io/service/11161/BC5h3cmj_400x400.jpg"
    },
    {
      "tool": "Presto",
      "logo": "https://img.stackshare.io/service/2606/zfcO78oI.png"
    },
    {
      "tool": "Fedora",
      "logo": "https://img.stackshare.io/service/5068/infinity-logo.png"
    },
    {
      "tool": "Azure Data Factory",
      "logo": "https://img.stackshare.io/service/6356/sni_tf5H_400x400.jpg"
    },
    {
      "tool": "Honeybadger",
      "logo": "https://img.stackshare.io/service/193/XWj_qQP8_400x400.jpg"
    },
    {
      "tool": "Salesforce Marketing Cloud",
      "logo": "https://img.stackshare.io/service/8520/mVUDo78h_400x400.jpg"
    },
    {
      "tool": "TypeORM",
      "logo": "https://img.stackshare.io/service/7419/20165699.png"
    },
    {
      "tool": "Google Cloud Functions",
      "logo": "https://img.stackshare.io/service/6672/google-cloud-functions.png"
    },
    {
      "tool": "Lucidchart",
      "logo": "https://img.stackshare.io/service/4223/lucidchart-06-535x535.png"
    },
    {
      "tool": "Firebase Hosting",
      "logo": "https://img.stackshare.io/service/6688/m3cEA33V_400x400.jpg"
    },
    {
      "tool": "Vue Router",
      "logo": "https://img.stackshare.io/service/6932/upM71pVR_400x400.jpg"
    },
    {
      "tool": "MySQL WorkBench",
      "logo": "https://img.stackshare.io/service/4319/descarga.jpeg"
    },
    {
      "tool": "Java EE",
      "logo": "https://img.stackshare.io/service/4522/652rxwyK_400x400.png"
    },
    {
      "tool": "Google Docs",
      "logo": "https://img.stackshare.io/service/4575/google-docs.png"
    },
    {
      "tool": "Splunk",
      "logo": "https://img.stackshare.io/service/1732/oru8eUWh_400x400.jpg"
    },
    {
      "tool": "Java 8",
      "logo": "https://img.stackshare.io/service/4702/java-8-logo.png"
    },
    {
      "tool": "Android Room",
      "logo": "https://img.stackshare.io/service/9379/XHLvU9Yg_400x400.png"
    },
    {
      "tool": "Loki",
      "logo": "https://img.stackshare.io/service/10079/loki.png"
    },
    {
      "tool": "Microsoft Visio",
      "logo": "https://img.stackshare.io/service/7466/visio-logo.jpg"
    },
    {
      "tool": "Apache Hive",
      "logo": "https://img.stackshare.io/service/1911/27eb4217dfd5cb2d579cb56bbcc7b290_400x400.jpeg"
    },
    {
      "tool": "OneDrive",
      "logo": "https://img.stackshare.io/service/1814/X4ZS9emh_400x400.png"
    },
    {
      "tool": "Moment.js",
      "logo": "https://img.stackshare.io/service/3643/Xrtdc94q_400x400.png"
    },
    {
      "tool": "LiteSpeed",
      "logo": "https://img.stackshare.io/service/2873/9lxca5AK_400x400.jpg"
    },
    {
      "tool": "Fastly",
      "logo": "https://img.stackshare.io/service/274/9V2sLNfw.png"
    },
    {
      "tool": "AWS CodePipeline",
      "logo": "https://img.stackshare.io/service/3297/aws-codepipeline.png"
    },
    {
      "tool": "Solr",
      "logo": "https://img.stackshare.io/service/1596/al3IkKF8.png"
    },
    {
      "tool": "Kubeflow",
      "logo": "https://img.stackshare.io/service/8052/EE9PAsVm_400x400.jpg"
    },
    {
      "tool": "IBM Watson",
      "logo": "https://img.stackshare.io/service/4696/preview.png"
    },
    {
      "tool": "SciPy",
      "logo": "https://img.stackshare.io/service/3303/scipyshiny_small.png"
    },
    {
      "tool": "WebdriverIO",
      "logo": "https://img.stackshare.io/service/4185/webdriver.io.png"
    },
    {
      "tool": "Java EE",
      "logo": "https://img.stackshare.io/service/4522/652rxwyK_400x400.png"
    },
    {
      "tool": "Kubeflow",
      "logo": "https://img.stackshare.io/service/8052/EE9PAsVm_400x400.jpg"
    },
    {
      "tool": "Pipedrive",
      "logo": "https://img.stackshare.io/service/2733/7NdrIqpR_400x400.jpg"
    },
    {
      "tool": "OneDrive",
      "logo": "https://img.stackshare.io/service/1814/X4ZS9emh_400x400.png"
    },
    {
      "tool": "SciPy",
      "logo": "https://img.stackshare.io/service/3303/scipyshiny_small.png"
    },
    {
      "tool": "Adobe Experience Manager",
      "logo": "https://img.stackshare.io/service/4343/8ei_UuLc_200x200.png"
    },
    {
      "tool": "LiteSpeed",
      "logo": "https://img.stackshare.io/service/2873/9lxca5AK_400x400.jpg"
    },
    {
      "tool": "Jira Service Desk",
      "logo": "https://img.stackshare.io/service/1860/oIyuo8uz_400x400.png"
    },
    {
      "tool": "IBM Watson",
      "logo": "https://img.stackshare.io/service/4696/preview.png"
    },
    {
      "tool": "Godot",
      "logo": "https://img.stackshare.io/service/10490/wZXPJXx__400x400.jpg"
    },
    {
      "tool": "redux-thunk",
      "logo": "https://img.stackshare.io/service/5448/13142323.png"
    },
    {
      "tool": "Fork",
      "logo": "https://img.stackshare.io/service/5672/logo1.png"
    },
    {
      "tool": "Bitbucket Pipelines",
      "logo": "https://img.stackshare.io/service/7452/35O2KIRX_400x400.jpg"
    },
    {
      "tool": "Expo",
      "logo": "https://img.stackshare.io/service/5795/FLrIEeNN.jpg"
    },
    {
      "tool": "Play",
      "logo": "https://img.stackshare.io/service/1013/HqN22PuY.png"
    },
    {
      "tool": "Algolia",
      "logo": "https://img.stackshare.io/service/589/iEEMVN5L_400x400.jpg"
    },
    {
      "tool": "Dialogflow",
      "logo": "https://img.stackshare.io/service/8463/S7C-2C6t_400x400.jpg"
    },
    {
      "tool": "NuGet",
      "logo": "https://img.stackshare.io/service/2637/6I3oEOP4_400x400.jpg"
    },
    {
      "tool": "Octopus Deploy",
      "logo": "https://img.stackshare.io/service/1341/preview.png"
    },
    {
      "tool": "DBeaver",
      "logo": "https://img.stackshare.io/service/3107/D0pB_eET_400x400.jpg"
    },
    {
      "tool": "ngrok",
      "logo": "https://img.stackshare.io/service/1309/ngrok.png"
    },
    {
      "tool": "Optimize",
      "logo": "https://img.stackshare.io/service/6719/optimize-360_icon.png"
    },
    {
      "tool": "Mattermost",
      "logo": "https://img.stackshare.io/service/3254/xiE1dr2s_400x400.jpg"
    },
    {
      "tool": "AWS Amplify",
      "logo": "https://img.stackshare.io/no-img-open-source.png"
    },
    {
      "tool": "Looker",
      "logo": "https://img.stackshare.io/service/1881/sR-yKoY-.jpg"
    },
    {
      "tool": "F#",
      "logo": "https://img.stackshare.io/service/2155/yRNL7yTW.png"
    },
    {
      "tool": "Octopus Deploy",
      "logo": "https://img.stackshare.io/service/1341/preview.png"
    },
    {
      "tool": "Vault",
      "logo": "https://img.stackshare.io/service/2905/vault.png"
    },
    {
      "tool": "Looker",
      "logo": "https://img.stackshare.io/service/1881/sR-yKoY-.jpg"
    },
    {
      "tool": "Semantic UI",
      "logo": "https://img.stackshare.io/service/1106/semantic-ui.png"
    },
    {
      "tool": "Mattermost",
      "logo": "https://img.stackshare.io/service/3254/xiE1dr2s_400x400.jpg"
    },
    {
      "tool": "NuGet",
      "logo": "https://img.stackshare.io/service/2637/6I3oEOP4_400x400.jpg"
    },
    {
      "tool": "Nexmo",
      "logo": "https://img.stackshare.io/service/318/-eqwAwiC.png"
    },
    {
      "tool": "Framer",
      "logo": "https://img.stackshare.io/service/826/BlCZdW9q.png"
    },
    {
      "tool": "Optimize",
      "logo": "https://img.stackshare.io/service/6719/optimize-360_icon.png"
    },
    {
      "tool": "Plotly",
      "logo": "https://img.stackshare.io/service/2385/5997976.jpeg"
    },
    {
      "tool": "OpenStack",
      "logo": "https://img.stackshare.io/service/770/GCPRyAva.png"
    },
    {
      "tool": "BrowserStack",
      "logo": "https://img.stackshare.io/service/182/0pyDMTyp.png"
    },
    {
      "tool": "Chart.js",
      "logo": "https://img.stackshare.io/service/3866/_GD1-XrU_400x400.jpg"
    },
    {
      "tool": "TestCafe",
      "logo": "https://img.stackshare.io/service/7532/W2FwS-Ry_400x400.jpg"
    },
    {
      "tool": "NativeScript",
      "logo": "https://img.stackshare.io/service/2605/_fBe-iYT.jpeg"
    },
    {
      "tool": "Hotjar",
      "logo": "https://img.stackshare.io/service/2207/BoZ1jvob_400x400.jpg"
    },
    {
      "tool": "Couchbase",
      "logo": "https://img.stackshare.io/service/1089/KMIbGY8C.png"
    },
    {
      "tool": "RubyMine",
      "logo": "https://img.stackshare.io/service/1454/icon_RubyMine.png"
    },
    {
      "tool": "Firebase Cloud Messaging",
      "logo": "https://img.stackshare.io/service/7670/m3cEA33V_400x400.jpg"
    },
    {
      "tool": "drawio",
      "logo": "https://img.stackshare.io/service/2450/Hh-vWsQ0_400x400.jpg"
    },
    {
      "tool": "Dash",
      "logo": "https://img.stackshare.io/service/2405/HB_dh5cX.png"
    },
    {
      "tool": "Checkstyle",
      "logo": "https://img.stackshare.io/service/2921/i3fm8awH_400x400.png"
    },
    {
      "tool": "JFrog Artifactory",
      "logo": "https://img.stackshare.io/service/4711/jfrog-artifactory-logo.png"
    },
    {
      "tool": "Gunicorn",
      "logo": "https://img.stackshare.io/service/1091/gunicorn.png"
    },
    {
      "tool": "CLion",
      "logo": "https://img.stackshare.io/service/1445/icon_CLion.png"
    },
    {
      "tool": "Liquibase",
      "logo": "https://img.stackshare.io/service/1398/y1As8_s5_400x400.jpg"
    },
    {
      "tool": "Emotion",
      "logo": "https://img.stackshare.io/service/8770/emotion-a76dfa0d18a0536af9e917cdb8f873b9-44576.png"
    },
    {
      "tool": "Amazon RDS for PostgreSQL",
      "logo": "https://img.stackshare.io/service/434/amazon-rds.png"
    },
    {
      "tool": "Gunicorn",
      "logo": "https://img.stackshare.io/service/1091/gunicorn.png"
    },
    {
      "tool": "Couchbase",
      "logo": "https://img.stackshare.io/service/1089/KMIbGY8C.png"
    },
    {
      "tool": "Optimize",
      "logo": "https://img.stackshare.io/service/6719/optimize-360_icon.png"
    },
    {
      "tool": "OpenStack",
      "logo": "https://img.stackshare.io/service/770/GCPRyAva.png"
    },
    {
      "tool": "Protobuf",
      "logo": "https://img.stackshare.io/service/4393/ma2jqJKH_400x400.png"
    },
    {
      "tool": "Databricks",
      "logo": "https://img.stackshare.io/service/9655/iJ_Wi0K4_400x400.png"
    },
    {
      "tool": "Koa",
      "logo": "https://img.stackshare.io/service/1726/5055057.png"
    },
    {
      "tool": "Hotjar",
      "logo": "https://img.stackshare.io/service/2207/BoZ1jvob_400x400.jpg"
    },
    {
      "tool": "Firebase Cloud Messaging",
      "logo": "https://img.stackshare.io/service/7670/m3cEA33V_400x400.jpg"
    },
    {
      "tool": "Eureka",
      "logo": "https://img.stackshare.io/service/2085/99V92_Sr.png"
    },
    {
      "tool": "Bokeh",
      "logo": "https://img.stackshare.io/service/3012/preview.png"
    },
    {
      "tool": "Lerna",
      "logo": "https://img.stackshare.io/service/6207/OwqAUSQi_400x400.jpg"
    },
    {
      "tool": "TestCafe",
      "logo": "https://img.stackshare.io/service/7532/W2FwS-Ry_400x400.jpg"
    },
    {
      "tool": "drawio",
      "logo": "https://img.stackshare.io/service/2450/Hh-vWsQ0_400x400.jpg"
    },
    {
      "tool": "Camunda",
      "logo": "https://img.stackshare.io/service/2972/2rR8wsn8_400x400.jpg"
    },
    {
      "tool": "Bootstrap Vue",
      "logo": "https://img.stackshare.io/service/8975/MNHNfucQ_400x400.jpg"
    },
    {
      "tool": "Prisma",
      "logo": "https://img.stackshare.io/service/8680/Logo_Symbol_White.jpg"
    },
    {
      "tool": "Lumen",
      "logo": "https://img.stackshare.io/service/2820/lumen.png"
    },
    {
      "tool": "Puma",
      "logo": "https://img.stackshare.io/service/1055/favicon.png"
    },
    {
      "tool": "Buefy",
      "logo": "https://img.stackshare.io/service/10410/26799900.png"
    },
    {
      "tool": "Telegram Bot API",
      "logo": "https://img.stackshare.io/service/4894/m6BFtJQW.png"
    },
    {
      "tool": "Matomo",
      "logo": "https://img.stackshare.io/service/8914/n0MGIAF6_400x400.jpg"
    },
    {
      "tool": "Bitrise",
      "logo": "https://img.stackshare.io/service/2686/wFlFGsF3_400x400.jpg"
    },
    {
      "tool": "Prisma",
      "logo": "https://img.stackshare.io/service/8680/Logo_Symbol_White.jpg"
    },
    {
      "tool": "Microsoft PowerApps",
      "logo": "https://img.stackshare.io/service/10896/L1-Nd17P_400x400.jpg"
    },
    {
      "tool": "Integromat",
      "logo": "https://img.stackshare.io/service/9161/ENLsPTUc_400x400.png"
    },
    {
      "tool": "Braze",
      "logo": "https://img.stackshare.io/service/9152/preview.png"
    },
    {
      "tool": "ArcGIS",
      "logo": "https://img.stackshare.io/service/4379/mjImnOJe_400x400.jpg"
    },
    {
      "tool": "Testrail",
      "logo": "https://img.stackshare.io/service/2724/rDzk-i_U_400x400.jpg"
    },
    {
      "tool": "rollup",
      "logo": "https://img.stackshare.io/service/4423/zE8RTn9E_400x400.jpg"
    },
    {
      "tool": "Paddle",
      "logo": "https://img.stackshare.io/service/4445/7-TO14fI_400x400.png"
    },
    {
      "tool": "MLflow",
      "logo": "https://img.stackshare.io/service/9078/mlflow.png"
    },
    {
      "tool": "Julia",
      "logo": "https://img.stackshare.io/service/3914/647b7cf75cb5662b96901bc521968e94.png"
    },
    {
      "tool": "LaunchDarkly",
      "logo": "https://img.stackshare.io/service/4506/preview.png"
    },
    {
      "tool": "k3s",
      "logo": "https://img.stackshare.io/service/10432/logo-k3s.png"
    },
    {
      "tool": "Buefy",
      "logo": "https://img.stackshare.io/service/10410/26799900.png"
    },
    {
      "tool": "React Storybook",
      "logo": "https://img.stackshare.io/service/4906/22632046.png"
    },
    {
      "tool": "YouTrack",
      "logo": "https://img.stackshare.io/service/1708/logo.png"
    },
    {
      "tool": "TestLink",
      "logo": "https://img.stackshare.io/service/9697/lone_ranger_400x400.png"
    },
    {
      "tool": "VMware Horizon Suite",
      "logo": "https://img.stackshare.io/service/417/xxr1e-Lu_400x400.jpg"
    },
    {
      "tool": "OpenVPN",
      "logo": "https://ucarecdn.com/01a270e0-e967-40df-b725-62598712622a/"
    },
    {
      "tool": "Google Cloud Storage",
      "logo": "https://img.stackshare.io/service/694/Cloud_Storage.png"
    },
    {
      "tool": "Telegram Bot API",
      "logo": "https://img.stackshare.io/service/4894/m6BFtJQW.png"
    },
    {
      "tool": "Karate DSL",
      "logo": "https://img.stackshare.io/service/10448/4s_HM6rX_400x400.jpg"
    },
    {
      "tool": "PySpark",
      "logo": "https://img.stackshare.io/service/9080/hNHMcixV_400x400.jpg"
    },
    {
      "tool": "Streamlit",
      "logo": "https://img.stackshare.io/service/11393/_jl26ArQ_400x400.jpg"
    },
    {
      "tool": "React Storybook",
      "logo": "https://img.stackshare.io/service/4906/22632046.png"
    },
    {
      "tool": "Prisma",
      "logo": "https://img.stackshare.io/service/8680/Logo_Symbol_White.jpg"
    },
    {
      "tool": "YouTrack",
      "logo": "https://img.stackshare.io/service/1708/logo.png"
    },
    {
      "tool": "Matomo",
      "logo": "https://img.stackshare.io/service/8914/n0MGIAF6_400x400.jpg"
    },
    {
      "tool": "three.js",
      "logo": "https://img.stackshare.io/service/5883/preview.png"
    },
    {
      "tool": "Google Cloud Storage",
      "logo": "https://img.stackshare.io/service/694/Cloud_Storage.png"
    },
    {
      "tool": "Karate DSL",
      "logo": "https://img.stackshare.io/service/10448/4s_HM6rX_400x400.jpg"
    },
    {
      "tool": "Braze",
      "logo": "https://img.stackshare.io/service/9152/preview.png"
    },
    {
      "tool": "Puma",
      "logo": "https://img.stackshare.io/service/1055/favicon.png"
    },
    {
      "tool": "Cloud Foundry",
      "logo": "https://img.stackshare.io/service/893/VJI_bxtd_200x200.jpg"
    },
    {
      "tool": "Paddle",
      "logo": "https://img.stackshare.io/service/4445/7-TO14fI_400x400.png"
    },
    {
      "tool": "ArcGIS",
      "logo": "https://img.stackshare.io/service/4379/mjImnOJe_400x400.jpg"
    },
    {
      "tool": "Katalon Studio",
      "logo": "https://img.stackshare.io/service/9955/cH1OMAo6_400x400.jpg"
    },
    {
      "tool": "LaunchDarkly",
      "logo": "https://img.stackshare.io/service/4506/preview.png"
    },
    {
      "tool": "rollup",
      "logo": "https://img.stackshare.io/service/4423/zE8RTn9E_400x400.jpg"
    },
    {
      "tool": "PySpark",
      "logo": "https://img.stackshare.io/service/9080/hNHMcixV_400x400.jpg"
    },
    {
      "tool": "k3s",
      "logo": "https://img.stackshare.io/service/10432/logo-k3s.png"
    },
    {
      "tool": "Buefy",
      "logo": "https://img.stackshare.io/service/10410/26799900.png"
    },
    {
      "tool": "MLflow",
      "logo": "https://img.stackshare.io/service/9078/mlflow.png"
    },
    {
      "tool": "Streamlit",
      "logo": "https://img.stackshare.io/service/11393/_jl26ArQ_400x400.jpg"
    },
    {
      "tool": "Jitsi",
      "logo": "https://img.stackshare.io/service/9412/V63YMKSb_400x400.jpg"
    },
    {
      "tool": "VMware Horizon Suite",
      "logo": "https://img.stackshare.io/service/417/xxr1e-Lu_400x400.jpg"
    },
    {
      "tool": "Mule",
      "logo": "https://img.stackshare.io/service/2859/DtPD4wxH_400x400.png"
    },
    {
      "tool": "Google Hangouts Chat",
      "logo": "https://img.stackshare.io/service/8558/mRHomqt.png"
    },
    {
      "tool": "Telegram Bot API",
      "logo": "https://img.stackshare.io/service/4894/m6BFtJQW.png"
    },
    {
      "tool": "Braze",
      "logo": "https://img.stackshare.io/service/9152/preview.png"
    },
    {
      "tool": "Portainer",
      "logo": "https://img.stackshare.io/service/5926/Qu-iixzV.jpg"
    },
    {
      "tool": "SendBird",
      "logo": "https://img.stackshare.io/service/4275/SB_Symbol_RGB_v3.0.jpg"
    },
    {
      "tool": "OpenLayers",
      "logo": "https://img.stackshare.io/service/3208/397ce8027eb036960f00dd5153d41993.png"
    },
    {
      "tool": "Jitsi",
      "logo": "https://img.stackshare.io/service/9412/V63YMKSb_400x400.jpg"
    },
    {
      "tool": "MLflow",
      "logo": "https://img.stackshare.io/service/9078/mlflow.png"
    },
    {
      "tool": "ArcGIS",
      "logo": "https://img.stackshare.io/service/4379/mjImnOJe_400x400.jpg"
    },
    {
      "tool": "Arch Linux",
      "logo": "https://img.stackshare.io/service/2635/arch_linux.png"
    },
    {
      "tool": "Google Hangouts Chat",
      "logo": "https://img.stackshare.io/service/8558/mRHomqt.png"
    },
    {
      "tool": "Buefy",
      "logo": "https://img.stackshare.io/service/10410/26799900.png"
    },
    {
      "tool": "Sumo Logic",
      "logo": "https://img.stackshare.io/service/370/Qz_ocsrM.jpeg"
    },
    {
      "tool": "AWS CodeBuild",
      "logo": "https://img.stackshare.io/service/6086/aws-codebuild.png"
    },
    {
      "tool": "k3s",
      "logo": "https://img.stackshare.io/service/10432/logo-k3s.png"
    },
    {
      "tool": "StackStorm",
      "logo": "https://img.stackshare.io/service/2348/VaMFEyf3.jpeg"
    },
    {
      "tool": "LaunchDarkly",
      "logo": "https://img.stackshare.io/service/4506/preview.png"
    },
    {
      "tool": "Streamlit",
      "logo": "https://img.stackshare.io/service/11393/_jl26ArQ_400x400.jpg"
    },
    {
      "tool": "Salesforce Service Cloud",
      "logo": "https://img.stackshare.io/service/8521/eibK7h2e_400x400.jpg"
    },
    {
      "tool": "Passenger",
      "logo": "https://img.stackshare.io/service/1054/icon.png"
    },
    {
      "tool": "Telegram Bot API",
      "logo": "https://img.stackshare.io/service/4894/m6BFtJQW.png"
    },
    {
      "tool": "FreshDesk",
      "logo": "https://img.stackshare.io/service/72/d0xmceuw_400x400.jpg"
    },
    {
      "tool": "UIkIt",
      "logo": "https://img.stackshare.io/service/1107/2247444e82685c05034fc296fc331472.png"
    },
    {
      "tool": "EasyOCR",
      "logo": "https://img.stackshare.io/service/12629/no-img.png"
    },
    {
      "tool": "Sleuth",
      "logo": "https://img.stackshare.io/service/12510/S_S79jan_400x400.jpg"
    },
    {
      "tool": "PHPUnit",
      "logo": "https://img.stackshare.io/service/1616/1_WsEnddd5Y4EgEHsT054kUQ.jpeg"
    },
    {
      "tool": "VMware Horizon Suite",
      "logo": "https://img.stackshare.io/service/417/xxr1e-Lu_400x400.jpg"
    },
    {
      "tool": "VMware Horizon Suite",
      "logo": "https://img.stackshare.io/service/417/xxr1e-Lu_400x400.jpg"
    },
    {
      "tool": "ArcGIS",
      "logo": "https://img.stackshare.io/service/4379/mjImnOJe_400x400.jpg"
    },
    {
      "tool": "rollup",
      "logo": "https://img.stackshare.io/service/4423/zE8RTn9E_400x400.jpg"
    },
    {
      "tool": "Salesforce Service Cloud",
      "logo": "https://img.stackshare.io/service/8521/eibK7h2e_400x400.jpg"
    },
    {
      "tool": "UIkIt",
      "logo": "https://img.stackshare.io/service/1107/2247444e82685c05034fc296fc331472.png"
    },
    {
      "tool": "Brave",
      "logo": "https://img.stackshare.io/service/7577/rO7aIdyp_400x400.jpg"
    },
    {
      "tool": "Spring Data",
      "logo": "https://img.stackshare.io/service/7624/IG6D4Ro2_400x400.png"
    },
    {
      "tool": "Streamlit",
      "logo": "https://img.stackshare.io/service/11393/_jl26ArQ_400x400.jpg"
    },
    {
      "tool": "k3s",
      "logo": "https://img.stackshare.io/service/10432/logo-k3s.png"
    },
    {
      "tool": "LaunchDarkly",
      "logo": "https://img.stackshare.io/service/4506/preview.png"
    },
    {
      "tool": "EasyOCR",
      "logo": "https://img.stackshare.io/service/12629/no-img.png"
    },
    {
      "tool": "Calendly",
      "logo": "https://img.stackshare.io/service/1310/UljSkwcI.png"
    },
    {
      "tool": "PHPUnit",
      "logo": "https://img.stackshare.io/service/1616/1_WsEnddd5Y4EgEHsT054kUQ.jpeg"
    },
    {
      "tool": "MSSQL",
      "logo": "https://img.stackshare.io/service/2445/ZKsJsucq_400x400.jpg"
    },
    {
      "tool": "Sleuth",
      "logo": "https://img.stackshare.io/service/12510/S_S79jan_400x400.jpg"
    },
    {
      "tool": "Gitea",
      "logo": "https://img.stackshare.io/service/6378/preview.png"
    },
    {
      "tool": "Stylus",
      "logo": "https://img.stackshare.io/service/1172/stylus.png"
    },
    {
      "tool": "Buefy",
      "logo": "https://img.stackshare.io/service/10410/26799900.png"
    },
    {
      "tool": "Drone.io",
      "logo": "https://img.stackshare.io/service/668/R_wMcCqN_400x400.png"
    },
    {
      "tool": "Adobe Analytics",
      "logo": "https://img.stackshare.io/service/2139/Iugn8n-F_400x400.png"
    },
    {
      "tool": "Coda",
      "logo": "https://img.stackshare.io/service/11707/TISjq2Y0_400x400.png"
    },
    {
      "tool": "Pingdom",
      "logo": "https://img.stackshare.io/service/106/usvDLKsY_400x400.png"
    },
    {
      "tool": "xUnit",
      "logo": "https://img.stackshare.io/service/3077/ca5a327feb49ddfe1f4b11548907e5a1_400x400.png"
    },
    {
      "tool": "Vue CLI",
      "logo": "https://img.stackshare.io/service/9559/upM71pVR_400x400.jpg"
    },
    {
      "tool": "Entity Framework",
      "logo": "https://img.stackshare.io/service/3251/no-img-open-source.png"
    }
  ]